{"lccn": "sn94056869", "place_of_publication": "Santa Fe, N.M.", "url": "http://chroniclingamerica.loc.gov/lccn/sn94056869.json", "start_year": "1890", "place": ["New Mexico--Santa Fe--Santa Fe"], "end_year": "1958", "issues": [{"date_issued": "1900-01-06", "url": "http://chroniclingamerica.loc.gov/lccn/sn94056869/1900-01-06/ed-1.json"}, {"date_issued": "1900-01-13", "url": "http://chroniclingamerica.loc.gov/lccn/sn94056869/1900-01-13/ed-1.json"}, {"date_issued": "1900-01-20", "url": "http://chroniclingamerica.loc.gov/lccn/sn94056869/1900-01-20/ed-1.json"}, {"date_issued": "1900-01-27", "url": "http://chroniclingamerica.loc.gov/lccn/sn94056869/1900-01-27/ed-1.json"}, {"date_issued": "1900-02-03", "url": "http://chroniclingamerica.loc.gov/lccn/sn94056869/1900-02-03/ed-1.json"}, {"date_issued": "1900-02-10", "url": "http://chroniclingamerica.loc.gov/lccn/sn94056869/1900-02-10/ed-1.json"}, {"date_issued": "1900-02-17", "url": "http://chroniclingamerica.loc.gov/lccn/sn94056869/1900-02-17/ed-1.json"}, {"date_issued": "1900-02-24", "url": "http://chroniclingamerica.loc.gov/lccn/sn94056869/1900-02-24/ed-1.json"}, {"date_issued": "1900-03-03", "url": "http://chroniclingamerica.loc.gov/lccn/sn94056869/1900-03-03/ed-1.json"}, {"date_issued": "1900-03-10", "url": "http://chroniclingamerica.loc.gov/lccn/sn94056869/1900-03-10/ed-1.json"}, {"date_issued": "1900-03-17", "url": "http://chroniclingamerica.loc.gov/lccn/sn94056869/1900-03-17/ed-1.json"}, {"date_issued": "1900-03-24", "url": "http://chroniclingamerica.loc.gov/lccn/sn94056869/1900-03-24/ed-1.json"}, {"date_issued": "1900-03-31", "url": "http://chroniclingamerica.loc.gov/lccn/sn94056869/1900-03-31/ed-1.json"}, {"date_issued": "1900-04-07", "url": "http://chroniclingamerica.loc.gov/lccn/sn94056869/1900-04-07/ed-1.json"}, {"date_issued": "1900-04-14", "url": "http://chroniclingamerica.loc.gov/lccn/sn94056869/1900-04-14/ed-1.json"}, {"date_issued": "1900-04-21", "url": "http://chroniclingamerica.loc.gov/lccn/sn94056869/1900-04-21/ed-1.json"}, {"date_issued": "1900-04-28", "url": "http://chroniclingamerica.loc.gov/lccn/sn94056869/1900-04-28/ed-1.json"}, {"date_issued": "1900-05-05", "url": "http://chroniclingamerica.loc.gov/lccn/sn94056869/1900-05-05/ed-1.json"}, {"date_issued": "1900-05-12", "url": "http://chroniclingamerica.loc.gov/lccn/sn94056869/1900-05-12/ed-1.json"}, {"date_issued": "1900-05-19", "url": "http://chroniclingamerica.loc.gov/lccn/sn94056869/1900-05-19/ed-1.json"}, {"date_issued": "1900-05-26", "url": "http://chroniclingamerica.loc.gov/lccn/sn94056869/1900-05-26/ed-1.json"}, {"date_issued": "1900-06-02", "url": "http://chroniclingamerica.loc.gov/lccn/sn94056869/1900-06-02/ed-1.json"}, {"date_issued": "1900-06-09", "url": "http://chroniclingamerica.loc.gov/lccn/sn94056869/1900-06-09/ed-1.json"}, {"date_issued": "1900-06-16", "url": "http://chroniclingamerica.loc.gov/lccn/sn94056869/1900-06-16/ed-1.json"}, {"date_issued": "1900-06-23", "url": "http://chroniclingamerica.loc.gov/lccn/sn94056869/1900-06-23/ed-1.json"}, {"date_issued": "1900-06-30", "url": "http://chroniclingamerica.loc.gov/lccn/sn94056869/1900-06-30/ed-1.json"}, {"date_issued": "1900-07-07", "url": "http://chroniclingamerica.loc.gov/lccn/sn94056869/1900-07-07/ed-1.json"}, {"date_issued": "1900-07-14", "url": "http://chroniclingamerica.loc.gov/lccn/sn94056869/1900-07-14/ed-1.json"}, {"date_issued": "1900-07-21", "url": "http://chroniclingamerica.loc.gov/lccn/sn94056869/1900-07-21/ed-1.json"}, {"date_issued": "1900-07-28", "url": "http://chroniclingamerica.loc.gov/lccn/sn94056869/1900-07-28/ed-1.json"}, {"date_issued": "1900-08-04", "url": "http://chroniclingamerica.loc.gov/lccn/sn94056869/1900-08-04/ed-1.json"}, {"date_issued": "1900-08-11", "url": "http://chroniclingamerica.loc.gov/lccn/sn94056869/1900-08-11/ed-1.json"}, {"date_issued": "1900-08-18", "url": "http://chroniclingamerica.loc.gov/lccn/sn94056869/1900-08-18/ed-1.json"}, {"date_issued": "1900-08-25", "url": "http://chroniclingamerica.loc.gov/lccn/sn94056869/1900-08-25/ed-1.json"}, {"date_issued": "1900-09-01", "url": "http://chroniclingamerica.loc.gov/lccn/sn94056869/1900-09-01/ed-1.json"}, {"date_issued": "1900-09-08", "url": "http://chroniclingamerica.loc.gov/lccn/sn94056869/1900-09-08/ed-1.json"}, {"date_issued": "1900-09-15", "url": "http://chroniclingamerica.loc.gov/lccn/sn94056869/1900-09-15/ed-1.json"}, {"date_issued": "1900-09-22", "url": "http://chroniclingamerica.loc.gov/lccn/sn94056869/1900-09-22/ed-1.json"}, {"date_issued": "1900-09-29", "url": "http://chroniclingamerica.loc.gov/lccn/sn94056869/1900-09-29/ed-1.json"}, {"date_issued": "1900-10-06", "url": "http://chroniclingamerica.loc.gov/lccn/sn94056869/1900-10-06/ed-1.json"}, {"date_issued": "1900-10-13", "url": "http://chroniclingamerica.loc.gov/lccn/sn94056869/1900-10-13/ed-1.json"}, {"date_issued": "1900-10-20", "url": "http://chroniclingamerica.loc.gov/lccn/sn94056869/1900-10-20/ed-1.json"}, {"date_issued": "1900-10-27", "url": "http://chroniclingamerica.loc.gov/lccn/sn94056869/1900-10-27/ed-1.json"}, {"date_issued": "1900-11-03", "url": "http://chroniclingamerica.loc.gov/lccn/sn94056869/1900-11-03/ed-1.json"}, {"date_issued": "1900-11-10", "url": "http://chroniclingamerica.loc.gov/lccn/sn94056869/1900-11-10/ed-1.json"}, {"date_issued": "1900-11-17", "url": "http://chroniclingamerica.loc.gov/lccn/sn94056869/1900-11-17/ed-1.json"}, {"date_issued": "1900-11-24", "url": "http://chroniclingamerica.loc.gov/lccn/sn94056869/1900-11-24/ed-1.json"}, {"date_issued": "1900-12-01", "url": "http://chroniclingamerica.loc.gov/lccn/sn94056869/1900-12-01/ed-1.json"}, {"date_issued": "1900-12-08", "url": "http://chroniclingamerica.loc.gov/lccn/sn94056869/1900-12-08/ed-1.json"}, {"date_issued": "1900-12-15", "url": "http://chroniclingamerica.loc.gov/lccn/sn94056869/1900-12-15/ed-1.json"}, {"date_issued": "1900-12-22", "url": "http://chroniclingamerica.loc.gov/lccn/sn94056869/1900-12-22/ed-1.json"}, {"date_issued": "1900-12-29", "url": "http://chroniclingamerica.loc.gov/lccn/sn94056869/1900-12-29/ed-1.json"}, {"date_issued": "1901-01-05", "url": "http://chroniclingamerica.loc.gov/lccn/sn94056869/1901-01-05/ed-1.json"}, {"date_issued": "1901-01-12", "url": "http://chroniclingamerica.loc.gov/lccn/sn94056869/1901-01-12/ed-1.json"}, {"date_issued": "1901-01-19", "url": "http://chroniclingamerica.loc.gov/lccn/sn94056869/1901-01-19/ed-1.json"}, {"date_issued": "1901-01-26", "url": "http://chroniclingamerica.loc.gov/lccn/sn94056869/1901-01-26/ed-1.json"}, {"date_issued": "1901-02-02", "url": "http://chroniclingamerica.loc.gov/lccn/sn94056869/1901-02-02/ed-1.json"}, {"date_issued": "1901-02-09", "url": "http://chroniclingamerica.loc.gov/lccn/sn94056869/1901-02-09/ed-1.json"}, {"date_issued": "1901-02-16", "url": "http://chroniclingamerica.loc.gov/lccn/sn94056869/1901-02-16/ed-1.json"}, {"date_issued": "1901-02-23", "url": "http://chroniclingamerica.loc.gov/lccn/sn94056869/1901-02-23/ed-1.json"}, {"date_issued": "1901-03-02", "url": "http://chroniclingamerica.loc.gov/lccn/sn94056869/1901-03-02/ed-1.json"}, {"date_issued": "1901-03-09", "url": "http://chroniclingamerica.loc.gov/lccn/sn94056869/1901-03-09/ed-1.json"}, {"date_issued": "1901-03-16", "url": "http://chroniclingamerica.loc.gov/lccn/sn94056869/1901-03-16/ed-1.json"}, {"date_issued": "1901-03-23", "url": "http://chroniclingamerica.loc.gov/lccn/sn94056869/1901-03-23/ed-1.json"}, {"date_issued": "1901-03-30", "url": "http://chroniclingamerica.loc.gov/lccn/sn94056869/1901-03-30/ed-1.json"}, {"date_issued": "1901-04-06", "url": "http://chroniclingamerica.loc.gov/lccn/sn94056869/1901-04-06/ed-1.json"}, {"date_issued": "1901-04-13", "url": "http://chroniclingamerica.loc.gov/lccn/sn94056869/1901-04-13/ed-1.json"}, {"date_issued": "1901-04-20", "url": "http://chroniclingamerica.loc.gov/lccn/sn94056869/1901-04-20/ed-1.json"}, {"date_issued": "1901-04-27", "url": "http://chroniclingamerica.loc.gov/lccn/sn94056869/1901-04-27/ed-1.json"}, {"date_issued": "1901-05-04", "url": "http://chroniclingamerica.loc.gov/lccn/sn94056869/1901-05-04/ed-1.json"}, {"date_issued": "1901-05-11", "url": "http://chroniclingamerica.loc.gov/lccn/sn94056869/1901-05-11/ed-1.json"}, {"date_issued": "1901-05-18", "url": "http://chroniclingamerica.loc.gov/lccn/sn94056869/1901-05-18/ed-1.json"}, {"date_issued": "1901-05-25", "url": "http://chroniclingamerica.loc.gov/lccn/sn94056869/1901-05-25/ed-1.json"}, {"date_issued": "1901-06-01", "url": "http://chroniclingamerica.loc.gov/lccn/sn94056869/1901-06-01/ed-1.json"}, {"date_issued": "1901-06-08", "url": "http://chroniclingamerica.loc.gov/lccn/sn94056869/1901-06-08/ed-1.json"}, {"date_issued": "1901-06-15", "url": "http://chroniclingamerica.loc.gov/lccn/sn94056869/1901-06-15/ed-1.json"}, {"date_issued": "1901-06-22", "url": "http://chroniclingamerica.loc.gov/lccn/sn94056869/1901-06-22/ed-1.json"}, {"date_issued": "1901-06-29", "url": "http://chroniclingamerica.loc.gov/lccn/sn94056869/1901-06-29/ed-1.json"}, {"date_issued": "1901-07-06", "url": "http://chroniclingamerica.loc.gov/lccn/sn94056869/1901-07-06/ed-1.json"}, {"date_issued": "1901-07-13", "url": "http://chroniclingamerica.loc.gov/lccn/sn94056869/1901-07-13/ed-1.json"}, {"date_issued": "1901-07-20", "url": "http://chroniclingamerica.loc.gov/lccn/sn94056869/1901-07-20/ed-1.json"}, {"date_issued": "1901-07-27", "url": "http://chroniclingamerica.loc.gov/lccn/sn94056869/1901-07-27/ed-1.json"}, {"date_issued": "1901-08-03", "url": "http://chroniclingamerica.loc.gov/lccn/sn94056869/1901-08-03/ed-1.json"}, {"date_issued": "1901-08-10", "url": "http://chroniclingamerica.loc.gov/lccn/sn94056869/1901-08-10/ed-1.json"}, {"date_issued": "1901-08-17", "url": "http://chroniclingamerica.loc.gov/lccn/sn94056869/1901-08-17/ed-1.json"}, {"date_issued": "1901-08-24", "url": "http://chroniclingamerica.loc.gov/lccn/sn94056869/1901-08-24/ed-1.json"}, {"date_issued": "1901-08-31", "url": "http://chroniclingamerica.loc.gov/lccn/sn94056869/1901-08-31/ed-1.json"}, {"date_issued": "1901-09-07", "url": "http://chroniclingamerica.loc.gov/lccn/sn94056869/1901-09-07/ed-1.json"}, {"date_issued": "1901-09-14", "url": "http://chroniclingamerica.loc.gov/lccn/sn94056869/1901-09-14/ed-1.json"}, {"date_issued": "1901-09-21", "url": "http://chroniclingamerica.loc.gov/lccn/sn94056869/1901-09-21/ed-1.json"}, {"date_issued": "1901-09-28", "url": "http://chroniclingamerica.loc.gov/lccn/sn94056869/1901-09-28/ed-1.json"}, {"date_issued": "1901-10-05", "url": "http://chroniclingamerica.loc.gov/lccn/sn94056869/1901-10-05/ed-1.json"}, {"date_issued": "1901-10-12", "url": "http://chroniclingamerica.loc.gov/lccn/sn94056869/1901-10-12/ed-1.json"}, {"date_issued": "1901-10-19", "url": "http://chroniclingamerica.loc.gov/lccn/sn94056869/1901-10-19/ed-1.json"}, {"date_issued": "1901-10-26", "url": "http://chroniclingamerica.loc.gov/lccn/sn94056869/1901-10-26/ed-1.json"}, {"date_issued": "1901-11-02", "url": "http://chroniclingamerica.loc.gov/lccn/sn94056869/1901-11-02/ed-1.json"}, {"date_issued": "1901-11-09", "url": "http://chroniclingamerica.loc.gov/lccn/sn94056869/1901-11-09/ed-1.json"}, {"date_issued": "1901-11-16", "url": "http://chroniclingamerica.loc.gov/lccn/sn94056869/1901-11-16/ed-1.json"}, {"date_issued": "1901-11-23", "url": "http://chroniclingamerica.loc.gov/lccn/sn94056869/1901-11-23/ed-1.json"}, {"date_issued": "1901-11-30", "url": "http://chroniclingamerica.loc.gov/lccn/sn94056869/1901-11-30/ed-1.json"}, {"date_issued": "1901-12-07", "url": "http://chroniclingamerica.loc.gov/lccn/sn94056869/1901-12-07/ed-1.json"}, {"date_issued": "1901-12-14", "url": "http://chroniclingamerica.loc.gov/lccn/sn94056869/1901-12-14/ed-1.json"}, {"date_issued": "1901-12-21", "url": "http://chroniclingamerica.loc.gov/lccn/sn94056869/1901-12-21/ed-1.json"}, {"date_issued": "1901-12-28", "url": "http://chroniclingamerica.loc.gov/lccn/sn94056869/1901-12-28/ed-1.json"}, {"date_issued": "1904-11-26", "url": "http://chroniclingamerica.loc.gov/lccn/sn94056869/1904-11-26/ed-1.json"}, {"date_issued": "1904-12-03", "url": "http://chroniclingamerica.loc.gov/lccn/sn94056869/1904-12-03/ed-1.json"}, {"date_issued": "1904-12-10", "url": "http://chroniclingamerica.loc.gov/lccn/sn94056869/1904-12-10/ed-1.json"}, {"date_issued": "1904-12-17", "url": "http://chroniclingamerica.loc.gov/lccn/sn94056869/1904-12-17/ed-1.json"}, {"date_issued": "1904-12-24", "url": "http://chroniclingamerica.loc.gov/lccn/sn94056869/1904-12-24/ed-1.json"}, {"date_issued": "1904-12-31", "url": "http://chroniclingamerica.loc.gov/lccn/sn94056869/1904-12-31/ed-1.json"}, {"date_issued": "1905-01-07", "url": "http://chroniclingamerica.loc.gov/lccn/sn94056869/1905-01-07/ed-1.json"}, {"date_issued": "1905-01-14", "url": "http://chroniclingamerica.loc.gov/lccn/sn94056869/1905-01-14/ed-1.json"}, {"date_issued": "1905-01-21", "url": "http://chroniclingamerica.loc.gov/lccn/sn94056869/1905-01-21/ed-1.json"}, {"date_issued": "1905-01-28", "url": "http://chroniclingamerica.loc.gov/lccn/sn94056869/1905-01-28/ed-1.json"}, {"date_issued": "1905-02-04", "url": "http://chroniclingamerica.loc.gov/lccn/sn94056869/1905-02-04/ed-1.json"}, {"date_issued": "1905-02-11", "url": "http://chroniclingamerica.loc.gov/lccn/sn94056869/1905-02-11/ed-1.json"}, {"date_issued": "1905-02-18", "url": "http://chroniclingamerica.loc.gov/lccn/sn94056869/1905-02-18/ed-1.json"}, {"date_issued": "1905-02-25", "url": "http://chroniclingamerica.loc.gov/lccn/sn94056869/1905-02-25/ed-1.json"}, {"date_issued": "1905-03-04", "url": "http://chroniclingamerica.loc.gov/lccn/sn94056869/1905-03-04/ed-1.json"}, {"date_issued": "1905-03-11", "url": "http://chroniclingamerica.loc.gov/lccn/sn94056869/1905-03-11/ed-1.json"}, {"date_issued": "1905-03-18", "url": "http://chroniclingamerica.loc.gov/lccn/sn94056869/1905-03-18/ed-1.json"}, {"date_issued": "1905-03-25", "url": "http://chroniclingamerica.loc.gov/lccn/sn94056869/1905-03-25/ed-1.json"}, {"date_issued": "1905-04-01", "url": "http://chroniclingamerica.loc.gov/lccn/sn94056869/1905-04-01/ed-1.json"}, {"date_issued": "1905-04-08", "url": "http://chroniclingamerica.loc.gov/lccn/sn94056869/1905-04-08/ed-1.json"}, {"date_issued": "1905-04-15", "url": "http://chroniclingamerica.loc.gov/lccn/sn94056869/1905-04-15/ed-1.json"}, {"date_issued": "1905-04-22", "url": "http://chroniclingamerica.loc.gov/lccn/sn94056869/1905-04-22/ed-1.json"}, {"date_issued": "1905-04-29", "url": "http://chroniclingamerica.loc.gov/lccn/sn94056869/1905-04-29/ed-1.json"}, {"date_issued": "1905-05-06", "url": "http://chroniclingamerica.loc.gov/lccn/sn94056869/1905-05-06/ed-1.json"}, {"date_issued": "1905-05-13", "url": "http://chroniclingamerica.loc.gov/lccn/sn94056869/1905-05-13/ed-1.json"}, {"date_issued": "1905-05-20", "url": "http://chroniclingamerica.loc.gov/lccn/sn94056869/1905-05-20/ed-1.json"}, {"date_issued": "1905-05-27", "url": "http://chroniclingamerica.loc.gov/lccn/sn94056869/1905-05-27/ed-1.json"}, {"date_issued": "1905-06-03", "url": "http://chroniclingamerica.loc.gov/lccn/sn94056869/1905-06-03/ed-1.json"}, {"date_issued": "1905-06-10", "url": "http://chroniclingamerica.loc.gov/lccn/sn94056869/1905-06-10/ed-1.json"}, {"date_issued": "1905-06-17", "url": "http://chroniclingamerica.loc.gov/lccn/sn94056869/1905-06-17/ed-1.json"}, {"date_issued": "1905-06-24", "url": "http://chroniclingamerica.loc.gov/lccn/sn94056869/1905-06-24/ed-1.json"}, {"date_issued": "1905-07-01", "url": "http://chroniclingamerica.loc.gov/lccn/sn94056869/1905-07-01/ed-1.json"}, {"date_issued": "1905-07-08", "url": "http://chroniclingamerica.loc.gov/lccn/sn94056869/1905-07-08/ed-1.json"}, {"date_issued": "1905-07-15", "url": "http://chroniclingamerica.loc.gov/lccn/sn94056869/1905-07-15/ed-1.json"}, {"date_issued": "1905-07-22", "url": "http://chroniclingamerica.loc.gov/lccn/sn94056869/1905-07-22/ed-1.json"}, {"date_issued": "1905-07-29", "url": "http://chroniclingamerica.loc.gov/lccn/sn94056869/1905-07-29/ed-1.json"}, {"date_issued": "1905-08-05", "url": "http://chroniclingamerica.loc.gov/lccn/sn94056869/1905-08-05/ed-1.json"}, {"date_issued": "1905-08-12", "url": "http://chroniclingamerica.loc.gov/lccn/sn94056869/1905-08-12/ed-1.json"}, {"date_issued": "1905-08-19", "url": "http://chroniclingamerica.loc.gov/lccn/sn94056869/1905-08-19/ed-1.json"}, {"date_issued": "1905-08-26", "url": "http://chroniclingamerica.loc.gov/lccn/sn94056869/1905-08-26/ed-1.json"}, {"date_issued": "1905-09-02", "url": "http://chroniclingamerica.loc.gov/lccn/sn94056869/1905-09-02/ed-1.json"}, {"date_issued": "1905-09-09", "url": "http://chroniclingamerica.loc.gov/lccn/sn94056869/1905-09-09/ed-1.json"}, {"date_issued": "1905-09-16", "url": "http://chroniclingamerica.loc.gov/lccn/sn94056869/1905-09-16/ed-1.json"}, {"date_issued": "1905-09-23", "url": "http://chroniclingamerica.loc.gov/lccn/sn94056869/1905-09-23/ed-1.json"}, {"date_issued": "1905-09-30", "url": "http://chroniclingamerica.loc.gov/lccn/sn94056869/1905-09-30/ed-1.json"}, {"date_issued": "1905-10-07", "url": "http://chroniclingamerica.loc.gov/lccn/sn94056869/1905-10-07/ed-1.json"}, {"date_issued": "1905-10-14", "url": "http://chroniclingamerica.loc.gov/lccn/sn94056869/1905-10-14/ed-1.json"}, {"date_issued": "1905-10-21", "url": "http://chroniclingamerica.loc.gov/lccn/sn94056869/1905-10-21/ed-1.json"}, {"date_issued": "1905-10-28", "url": "http://chroniclingamerica.loc.gov/lccn/sn94056869/1905-10-28/ed-1.json"}, {"date_issued": "1905-11-04", "url": "http://chroniclingamerica.loc.gov/lccn/sn94056869/1905-11-04/ed-1.json"}, {"date_issued": "1905-11-11", "url": "http://chroniclingamerica.loc.gov/lccn/sn94056869/1905-11-11/ed-1.json"}, {"date_issued": "1905-11-18", "url": "http://chroniclingamerica.loc.gov/lccn/sn94056869/1905-11-18/ed-1.json"}, {"date_issued": "1905-11-25", "url": "http://chroniclingamerica.loc.gov/lccn/sn94056869/1905-11-25/ed-1.json"}, {"date_issued": "1905-12-02", "url": "http://chroniclingamerica.loc.gov/lccn/sn94056869/1905-12-02/ed-1.json"}, {"date_issued": "1905-12-09", "url": "http://chroniclingamerica.loc.gov/lccn/sn94056869/1905-12-09/ed-1.json"}, {"date_issued": "1906-01-06", "url": "http://chroniclingamerica.loc.gov/lccn/sn94056869/1906-01-06/ed-1.json"}, {"date_issued": "1906-01-13", "url": "http://chroniclingamerica.loc.gov/lccn/sn94056869/1906-01-13/ed-1.json"}, {"date_issued": "1906-01-20", "url": "http://chroniclingamerica.loc.gov/lccn/sn94056869/1906-01-20/ed-1.json"}, {"date_issued": "1906-01-27", "url": "http://chroniclingamerica.loc.gov/lccn/sn94056869/1906-01-27/ed-1.json"}, {"date_issued": "1906-02-03", "url": "http://chroniclingamerica.loc.gov/lccn/sn94056869/1906-02-03/ed-1.json"}, {"date_issued": "1906-02-10", "url": "http://chroniclingamerica.loc.gov/lccn/sn94056869/1906-02-10/ed-1.json"}, {"date_issued": "1906-02-17", "url": "http://chroniclingamerica.loc.gov/lccn/sn94056869/1906-02-17/ed-1.json"}, {"date_issued": "1906-02-24", "url": "http://chroniclingamerica.loc.gov/lccn/sn94056869/1906-02-24/ed-1.json"}, {"date_issued": "1906-03-03", "url": "http://chroniclingamerica.loc.gov/lccn/sn94056869/1906-03-03/ed-1.json"}, {"date_issued": "1906-03-10", "url": "http://chroniclingamerica.loc.gov/lccn/sn94056869/1906-03-10/ed-1.json"}, {"date_issued": "1906-03-17", "url": "http://chroniclingamerica.loc.gov/lccn/sn94056869/1906-03-17/ed-1.json"}, {"date_issued": "1906-03-24", "url": "http://chroniclingamerica.loc.gov/lccn/sn94056869/1906-03-24/ed-1.json"}, {"date_issued": "1906-03-31", "url": "http://chroniclingamerica.loc.gov/lccn/sn94056869/1906-03-31/ed-1.json"}, {"date_issued": "1906-04-07", "url": "http://chroniclingamerica.loc.gov/lccn/sn94056869/1906-04-07/ed-1.json"}, {"date_issued": "1906-04-14", "url": "http://chroniclingamerica.loc.gov/lccn/sn94056869/1906-04-14/ed-1.json"}, {"date_issued": "1906-04-21", "url": "http://chroniclingamerica.loc.gov/lccn/sn94056869/1906-04-21/ed-1.json"}, {"date_issued": "1906-04-28", "url": "http://chroniclingamerica.loc.gov/lccn/sn94056869/1906-04-28/ed-1.json"}, {"date_issued": "1906-05-05", "url": "http://chroniclingamerica.loc.gov/lccn/sn94056869/1906-05-05/ed-1.json"}, {"date_issued": "1906-05-12", "url": "http://chroniclingamerica.loc.gov/lccn/sn94056869/1906-05-12/ed-1.json"}, {"date_issued": "1906-05-19", "url": "http://chroniclingamerica.loc.gov/lccn/sn94056869/1906-05-19/ed-1.json"}, {"date_issued": "1906-05-26", "url": "http://chroniclingamerica.loc.gov/lccn/sn94056869/1906-05-26/ed-1.json"}, {"date_issued": "1906-06-02", "url": "http://chroniclingamerica.loc.gov/lccn/sn94056869/1906-06-02/ed-1.json"}, {"date_issued": "1906-06-09", "url": "http://chroniclingamerica.loc.gov/lccn/sn94056869/1906-06-09/ed-1.json"}, {"date_issued": "1906-06-16", "url": "http://chroniclingamerica.loc.gov/lccn/sn94056869/1906-06-16/ed-1.json"}, {"date_issued": "1906-06-23", "url": "http://chroniclingamerica.loc.gov/lccn/sn94056869/1906-06-23/ed-1.json"}, {"date_issued": "1906-06-30", "url": "http://chroniclingamerica.loc.gov/lccn/sn94056869/1906-06-30/ed-1.json"}, {"date_issued": "1906-07-07", "url": "http://chroniclingamerica.loc.gov/lccn/sn94056869/1906-07-07/ed-1.json"}, {"date_issued": "1906-07-14", "url": "http://chroniclingamerica.loc.gov/lccn/sn94056869/1906-07-14/ed-1.json"}, {"date_issued": "1906-07-21", "url": "http://chroniclingamerica.loc.gov/lccn/sn94056869/1906-07-21/ed-1.json"}, {"date_issued": "1906-07-28", "url": "http://chroniclingamerica.loc.gov/lccn/sn94056869/1906-07-28/ed-1.json"}, {"date_issued": "1906-08-04", "url": "http://chroniclingamerica.loc.gov/lccn/sn94056869/1906-08-04/ed-1.json"}, {"date_issued": "1906-08-11", "url": "http://chroniclingamerica.loc.gov/lccn/sn94056869/1906-08-11/ed-1.json"}, {"date_issued": "1906-08-18", "url": "http://chroniclingamerica.loc.gov/lccn/sn94056869/1906-08-18/ed-1.json"}, {"date_issued": "1906-08-25", "url": "http://chroniclingamerica.loc.gov/lccn/sn94056869/1906-08-25/ed-1.json"}, {"date_issued": "1906-09-01", "url": "http://chroniclingamerica.loc.gov/lccn/sn94056869/1906-09-01/ed-1.json"}, {"date_issued": "1906-09-08", "url": "http://chroniclingamerica.loc.gov/lccn/sn94056869/1906-09-08/ed-1.json"}, {"date_issued": "1906-09-15", "url": "http://chroniclingamerica.loc.gov/lccn/sn94056869/1906-09-15/ed-1.json"}, {"date_issued": "1906-09-22", "url": "http://chroniclingamerica.loc.gov/lccn/sn94056869/1906-09-22/ed-1.json"}, {"date_issued": "1906-09-29", "url": "http://chroniclingamerica.loc.gov/lccn/sn94056869/1906-09-29/ed-1.json"}, {"date_issued": "1906-10-06", "url": "http://chroniclingamerica.loc.gov/lccn/sn94056869/1906-10-06/ed-1.json"}, {"date_issued": "1906-10-13", "url": "http://chroniclingamerica.loc.gov/lccn/sn94056869/1906-10-13/ed-1.json"}, {"date_issued": "1906-10-20", "url": "http://chroniclingamerica.loc.gov/lccn/sn94056869/1906-10-20/ed-1.json"}, {"date_issued": "1906-10-27", "url": "http://chroniclingamerica.loc.gov/lccn/sn94056869/1906-10-27/ed-1.json"}, {"date_issued": "1906-11-03", "url": "http://chroniclingamerica.loc.gov/lccn/sn94056869/1906-11-03/ed-1.json"}, {"date_issued": "1906-11-10", "url": "http://chroniclingamerica.loc.gov/lccn/sn94056869/1906-11-10/ed-1.json"}, {"date_issued": "1906-11-17", "url": "http://chroniclingamerica.loc.gov/lccn/sn94056869/1906-11-17/ed-1.json"}, {"date_issued": "1906-11-24", "url": "http://chroniclingamerica.loc.gov/lccn/sn94056869/1906-11-24/ed-1.json"}, {"date_issued": "1906-12-01", "url": "http://chroniclingamerica.loc.gov/lccn/sn94056869/1906-12-01/ed-1.json"}, {"date_issued": "1906-12-08", "url": "http://chroniclingamerica.loc.gov/lccn/sn94056869/1906-12-08/ed-1.json"}, {"date_issued": "1906-12-15", "url": "http://chroniclingamerica.loc.gov/lccn/sn94056869/1906-12-15/ed-1.json"}, {"date_issued": "1906-12-22", "url": "http://chroniclingamerica.loc.gov/lccn/sn94056869/1906-12-22/ed-1.json"}, {"date_issued": "1906-12-29", "url": "http://chroniclingamerica.loc.gov/lccn/sn94056869/1906-12-29/ed-1.json"}, {"date_issued": "1907-01-05", "url": "http://chroniclingamerica.loc.gov/lccn/sn94056869/1907-01-05/ed-1.json"}, {"date_issued": "1907-01-12", "url": "http://chroniclingamerica.loc.gov/lccn/sn94056869/1907-01-12/ed-1.json"}, {"date_issued": "1907-01-19", "url": "http://chroniclingamerica.loc.gov/lccn/sn94056869/1907-01-19/ed-1.json"}, {"date_issued": "1907-01-26", "url": "http://chroniclingamerica.loc.gov/lccn/sn94056869/1907-01-26/ed-1.json"}, {"date_issued": "1907-02-02", "url": "http://chroniclingamerica.loc.gov/lccn/sn94056869/1907-02-02/ed-1.json"}, {"date_issued": "1907-02-09", "url": "http://chroniclingamerica.loc.gov/lccn/sn94056869/1907-02-09/ed-1.json"}, {"date_issued": "1907-02-16", "url": "http://chroniclingamerica.loc.gov/lccn/sn94056869/1907-02-16/ed-1.json"}, {"date_issued": "1907-02-23", "url": "http://chroniclingamerica.loc.gov/lccn/sn94056869/1907-02-23/ed-1.json"}, {"date_issued": "1907-03-02", "url": "http://chroniclingamerica.loc.gov/lccn/sn94056869/1907-03-02/ed-1.json"}, {"date_issued": "1907-03-09", "url": "http://chroniclingamerica.loc.gov/lccn/sn94056869/1907-03-09/ed-1.json"}, {"date_issued": "1907-03-16", "url": "http://chroniclingamerica.loc.gov/lccn/sn94056869/1907-03-16/ed-1.json"}, {"date_issued": "1907-03-23", "url": "http://chroniclingamerica.loc.gov/lccn/sn94056869/1907-03-23/ed-1.json"}, {"date_issued": "1907-03-30", "url": "http://chroniclingamerica.loc.gov/lccn/sn94056869/1907-03-30/ed-1.json"}, {"date_issued": "1907-04-06", "url": "http://chroniclingamerica.loc.gov/lccn/sn94056869/1907-04-06/ed-1.json"}, {"date_issued": "1907-04-13", "url": "http://chroniclingamerica.loc.gov/lccn/sn94056869/1907-04-13/ed-1.json"}, {"date_issued": "1907-04-20", "url": "http://chroniclingamerica.loc.gov/lccn/sn94056869/1907-04-20/ed-1.json"}, {"date_issued": "1907-04-27", "url": "http://chroniclingamerica.loc.gov/lccn/sn94056869/1907-04-27/ed-1.json"}, {"date_issued": "1907-05-04", "url": "http://chroniclingamerica.loc.gov/lccn/sn94056869/1907-05-04/ed-1.json"}, {"date_issued": "1907-05-11", "url": "http://chroniclingamerica.loc.gov/lccn/sn94056869/1907-05-11/ed-1.json"}, {"date_issued": "1907-05-18", "url": "http://chroniclingamerica.loc.gov/lccn/sn94056869/1907-05-18/ed-1.json"}, {"date_issued": "1907-05-25", "url": "http://chroniclingamerica.loc.gov/lccn/sn94056869/1907-05-25/ed-1.json"}, {"date_issued": "1907-06-01", "url": "http://chroniclingamerica.loc.gov/lccn/sn94056869/1907-06-01/ed-1.json"}, {"date_issued": "1907-06-08", "url": "http://chroniclingamerica.loc.gov/lccn/sn94056869/1907-06-08/ed-1.json"}, {"date_issued": "1907-06-15", "url": "http://chroniclingamerica.loc.gov/lccn/sn94056869/1907-06-15/ed-1.json"}, {"date_issued": "1907-06-22", "url": "http://chroniclingamerica.loc.gov/lccn/sn94056869/1907-06-22/ed-1.json"}, {"date_issued": "1907-06-29", "url": "http://chroniclingamerica.loc.gov/lccn/sn94056869/1907-06-29/ed-1.json"}, {"date_issued": "1907-07-06", "url": "http://chroniclingamerica.loc.gov/lccn/sn94056869/1907-07-06/ed-1.json"}, {"date_issued": "1907-07-13", "url": "http://chroniclingamerica.loc.gov/lccn/sn94056869/1907-07-13/ed-1.json"}, {"date_issued": "1907-07-20", "url": "http://chroniclingamerica.loc.gov/lccn/sn94056869/1907-07-20/ed-1.json"}, {"date_issued": "1907-07-27", "url": "http://chroniclingamerica.loc.gov/lccn/sn94056869/1907-07-27/ed-1.json"}, {"date_issued": "1907-08-03", "url": "http://chroniclingamerica.loc.gov/lccn/sn94056869/1907-08-03/ed-1.json"}, {"date_issued": "1907-08-10", "url": "http://chroniclingamerica.loc.gov/lccn/sn94056869/1907-08-10/ed-1.json"}, {"date_issued": "1907-08-17", "url": "http://chroniclingamerica.loc.gov/lccn/sn94056869/1907-08-17/ed-1.json"}, {"date_issued": "1907-08-24", "url": "http://chroniclingamerica.loc.gov/lccn/sn94056869/1907-08-24/ed-1.json"}, {"date_issued": "1907-08-31", "url": "http://chroniclingamerica.loc.gov/lccn/sn94056869/1907-08-31/ed-1.json"}, {"date_issued": "1907-09-07", "url": "http://chroniclingamerica.loc.gov/lccn/sn94056869/1907-09-07/ed-1.json"}, {"date_issued": "1907-09-14", "url": "http://chroniclingamerica.loc.gov/lccn/sn94056869/1907-09-14/ed-1.json"}, {"date_issued": "1907-09-21", "url": "http://chroniclingamerica.loc.gov/lccn/sn94056869/1907-09-21/ed-1.json"}, {"date_issued": "1907-10-05", "url": "http://chroniclingamerica.loc.gov/lccn/sn94056869/1907-10-05/ed-1.json"}, {"date_issued": "1907-10-12", "url": "http://chroniclingamerica.loc.gov/lccn/sn94056869/1907-10-12/ed-1.json"}, {"date_issued": "1907-10-19", "url": "http://chroniclingamerica.loc.gov/lccn/sn94056869/1907-10-19/ed-1.json"}, {"date_issued": "1907-10-26", "url": "http://chroniclingamerica.loc.gov/lccn/sn94056869/1907-10-26/ed-1.json"}, {"date_issued": "1907-11-02", "url": "http://chroniclingamerica.loc.gov/lccn/sn94056869/1907-11-02/ed-1.json"}, {"date_issued": "1907-11-09", "url": "http://chroniclingamerica.loc.gov/lccn/sn94056869/1907-11-09/ed-1.json"}, {"date_issued": "1907-11-16", "url": "http://chroniclingamerica.loc.gov/lccn/sn94056869/1907-11-16/ed-1.json"}, {"date_issued": "1907-11-23", "url": "http://chroniclingamerica.loc.gov/lccn/sn94056869/1907-11-23/ed-1.json"}, {"date_issued": "1907-11-30", "url": "http://chroniclingamerica.loc.gov/lccn/sn94056869/1907-11-30/ed-1.json"}, {"date_issued": "1907-12-07", "url": "http://chroniclingamerica.loc.gov/lccn/sn94056869/1907-12-07/ed-1.json"}, {"date_issued": "1907-12-14", "url": "http://chroniclingamerica.loc.gov/lccn/sn94056869/1907-12-14/ed-1.json"}, {"date_issued": "1907-12-21", "url": "http://chroniclingamerica.loc.gov/lccn/sn94056869/1907-12-21/ed-1.json"}, {"date_issued": "1907-12-28", "url": "http://chroniclingamerica.loc.gov/lccn/sn94056869/1907-12-28/ed-1.json"}, {"date_issued": "1908-01-04", "url": "http://chroniclingamerica.loc.gov/lccn/sn94056869/1908-01-04/ed-1.json"}, {"date_issued": "1908-01-11", "url": "http://chroniclingamerica.loc.gov/lccn/sn94056869/1908-01-11/ed-1.json"}, {"date_issued": "1908-01-18", "url": "http://chroniclingamerica.loc.gov/lccn/sn94056869/1908-01-18/ed-1.json"}, {"date_issued": "1908-01-25", "url": "http://chroniclingamerica.loc.gov/lccn/sn94056869/1908-01-25/ed-1.json"}, {"date_issued": "1908-02-01", "url": "http://chroniclingamerica.loc.gov/lccn/sn94056869/1908-02-01/ed-1.json"}, {"date_issued": "1908-02-08", "url": "http://chroniclingamerica.loc.gov/lccn/sn94056869/1908-02-08/ed-1.json"}, {"date_issued": "1908-02-15", "url": "http://chroniclingamerica.loc.gov/lccn/sn94056869/1908-02-15/ed-1.json"}, {"date_issued": "1908-02-22", "url": "http://chroniclingamerica.loc.gov/lccn/sn94056869/1908-02-22/ed-1.json"}, {"date_issued": "1908-02-29", "url": "http://chroniclingamerica.loc.gov/lccn/sn94056869/1908-02-29/ed-1.json"}, {"date_issued": "1908-03-07", "url": "http://chroniclingamerica.loc.gov/lccn/sn94056869/1908-03-07/ed-1.json"}, {"date_issued": "1908-03-14", "url": "http://chroniclingamerica.loc.gov/lccn/sn94056869/1908-03-14/ed-1.json"}, {"date_issued": "1908-03-21", "url": "http://chroniclingamerica.loc.gov/lccn/sn94056869/1908-03-21/ed-1.json"}, {"date_issued": "1908-03-28", "url": "http://chroniclingamerica.loc.gov/lccn/sn94056869/1908-03-28/ed-1.json"}, {"date_issued": "1908-04-04", "url": "http://chroniclingamerica.loc.gov/lccn/sn94056869/1908-04-04/ed-1.json"}, {"date_issued": "1908-04-11", "url": "http://chroniclingamerica.loc.gov/lccn/sn94056869/1908-04-11/ed-1.json"}, {"date_issued": "1908-04-18", "url": "http://chroniclingamerica.loc.gov/lccn/sn94056869/1908-04-18/ed-1.json"}, {"date_issued": "1908-04-25", "url": "http://chroniclingamerica.loc.gov/lccn/sn94056869/1908-04-25/ed-1.json"}, {"date_issued": "1908-05-02", "url": "http://chroniclingamerica.loc.gov/lccn/sn94056869/1908-05-02/ed-1.json"}, {"date_issued": "1908-05-09", "url": "http://chroniclingamerica.loc.gov/lccn/sn94056869/1908-05-09/ed-1.json"}, {"date_issued": "1908-05-16", "url": "http://chroniclingamerica.loc.gov/lccn/sn94056869/1908-05-16/ed-1.json"}, {"date_issued": "1908-05-23", "url": "http://chroniclingamerica.loc.gov/lccn/sn94056869/1908-05-23/ed-1.json"}, {"date_issued": "1908-05-30", "url": "http://chroniclingamerica.loc.gov/lccn/sn94056869/1908-05-30/ed-1.json"}, {"date_issued": "1908-06-06", "url": "http://chroniclingamerica.loc.gov/lccn/sn94056869/1908-06-06/ed-1.json"}, {"date_issued": "1908-06-13", "url": "http://chroniclingamerica.loc.gov/lccn/sn94056869/1908-06-13/ed-1.json"}, {"date_issued": "1908-06-20", "url": "http://chroniclingamerica.loc.gov/lccn/sn94056869/1908-06-20/ed-1.json"}, {"date_issued": "1908-06-27", "url": "http://chroniclingamerica.loc.gov/lccn/sn94056869/1908-06-27/ed-1.json"}, {"date_issued": "1908-07-04", "url": "http://chroniclingamerica.loc.gov/lccn/sn94056869/1908-07-04/ed-1.json"}, {"date_issued": "1908-07-11", "url": "http://chroniclingamerica.loc.gov/lccn/sn94056869/1908-07-11/ed-1.json"}, {"date_issued": "1908-07-18", "url": "http://chroniclingamerica.loc.gov/lccn/sn94056869/1908-07-18/ed-1.json"}, {"date_issued": "1908-07-25", "url": "http://chroniclingamerica.loc.gov/lccn/sn94056869/1908-07-25/ed-1.json"}, {"date_issued": "1908-08-01", "url": "http://chroniclingamerica.loc.gov/lccn/sn94056869/1908-08-01/ed-1.json"}, {"date_issued": "1908-08-08", "url": "http://chroniclingamerica.loc.gov/lccn/sn94056869/1908-08-08/ed-1.json"}, {"date_issued": "1908-08-15", "url": "http://chroniclingamerica.loc.gov/lccn/sn94056869/1908-08-15/ed-1.json"}, {"date_issued": "1908-08-22", "url": "http://chroniclingamerica.loc.gov/lccn/sn94056869/1908-08-22/ed-1.json"}, {"date_issued": "1908-08-29", "url": "http://chroniclingamerica.loc.gov/lccn/sn94056869/1908-08-29/ed-1.json"}, {"date_issued": "1908-09-05", "url": "http://chroniclingamerica.loc.gov/lccn/sn94056869/1908-09-05/ed-1.json"}, {"date_issued": "1908-09-12", "url": "http://chroniclingamerica.loc.gov/lccn/sn94056869/1908-09-12/ed-1.json"}, {"date_issued": "1908-09-19", "url": "http://chroniclingamerica.loc.gov/lccn/sn94056869/1908-09-19/ed-1.json"}, {"date_issued": "1908-09-26", "url": "http://chroniclingamerica.loc.gov/lccn/sn94056869/1908-09-26/ed-1.json"}, {"date_issued": "1908-10-03", "url": "http://chroniclingamerica.loc.gov/lccn/sn94056869/1908-10-03/ed-1.json"}, {"date_issued": "1908-10-10", "url": "http://chroniclingamerica.loc.gov/lccn/sn94056869/1908-10-10/ed-1.json"}, {"date_issued": "1908-10-17", "url": "http://chroniclingamerica.loc.gov/lccn/sn94056869/1908-10-17/ed-1.json"}, {"date_issued": "1908-10-24", "url": "http://chroniclingamerica.loc.gov/lccn/sn94056869/1908-10-24/ed-1.json"}, {"date_issued": "1908-10-31", "url": "http://chroniclingamerica.loc.gov/lccn/sn94056869/1908-10-31/ed-1.json"}, {"date_issued": "1908-11-07", "url": "http://chroniclingamerica.loc.gov/lccn/sn94056869/1908-11-07/ed-1.json"}, {"date_issued": "1908-11-14", "url": "http://chroniclingamerica.loc.gov/lccn/sn94056869/1908-11-14/ed-1.json"}, {"date_issued": "1908-11-21", "url": "http://chroniclingamerica.loc.gov/lccn/sn94056869/1908-11-21/ed-1.json"}, {"date_issued": "1908-11-28", "url": "http://chroniclingamerica.loc.gov/lccn/sn94056869/1908-11-28/ed-1.json"}, {"date_issued": "1908-12-05", "url": "http://chroniclingamerica.loc.gov/lccn/sn94056869/1908-12-05/ed-1.json"}, {"date_issued": "1908-12-12", "url": "http://chroniclingamerica.loc.gov/lccn/sn94056869/1908-12-12/ed-1.json"}, {"date_issued": "1908-12-19", "url": "http://chroniclingamerica.loc.gov/lccn/sn94056869/1908-12-19/ed-1.json"}, {"date_issued": "1908-12-26", "url": "http://chroniclingamerica.loc.gov/lccn/sn94056869/1908-12-26/ed-1.json"}, {"date_issued": "1909-01-02", "url": "http://chroniclingamerica.loc.gov/lccn/sn94056869/1909-01-02/ed-1.json"}, {"date_issued": "1909-01-09", "url": "http://chroniclingamerica.loc.gov/lccn/sn94056869/1909-01-09/ed-1.json"}, {"date_issued": "1909-01-16", "url": "http://chroniclingamerica.loc.gov/lccn/sn94056869/1909-01-16/ed-1.json"}, {"date_issued": "1909-01-23", "url": "http://chroniclingamerica.loc.gov/lccn/sn94056869/1909-01-23/ed-1.json"}, {"date_issued": "1909-01-30", "url": "http://chroniclingamerica.loc.gov/lccn/sn94056869/1909-01-30/ed-1.json"}, {"date_issued": "1909-02-06", "url": "http://chroniclingamerica.loc.gov/lccn/sn94056869/1909-02-06/ed-1.json"}, {"date_issued": "1909-02-13", "url": "http://chroniclingamerica.loc.gov/lccn/sn94056869/1909-02-13/ed-1.json"}, {"date_issued": "1909-02-20", "url": "http://chroniclingamerica.loc.gov/lccn/sn94056869/1909-02-20/ed-1.json"}, {"date_issued": "1909-02-27", "url": "http://chroniclingamerica.loc.gov/lccn/sn94056869/1909-02-27/ed-1.json"}, {"date_issued": "1909-03-06", "url": "http://chroniclingamerica.loc.gov/lccn/sn94056869/1909-03-06/ed-1.json"}, {"date_issued": "1909-03-13", "url": "http://chroniclingamerica.loc.gov/lccn/sn94056869/1909-03-13/ed-1.json"}, {"date_issued": "1909-03-20", "url": "http://chroniclingamerica.loc.gov/lccn/sn94056869/1909-03-20/ed-1.json"}, {"date_issued": "1909-03-27", "url": "http://chroniclingamerica.loc.gov/lccn/sn94056869/1909-03-27/ed-1.json"}, {"date_issued": "1909-04-03", "url": "http://chroniclingamerica.loc.gov/lccn/sn94056869/1909-04-03/ed-1.json"}, {"date_issued": "1909-04-10", "url": "http://chroniclingamerica.loc.gov/lccn/sn94056869/1909-04-10/ed-1.json"}, {"date_issued": "1909-04-17", "url": "http://chroniclingamerica.loc.gov/lccn/sn94056869/1909-04-17/ed-1.json"}, {"date_issued": "1909-04-24", "url": "http://chroniclingamerica.loc.gov/lccn/sn94056869/1909-04-24/ed-1.json"}, {"date_issued": "1909-05-01", "url": "http://chroniclingamerica.loc.gov/lccn/sn94056869/1909-05-01/ed-1.json"}, {"date_issued": "1909-05-08", "url": "http://chroniclingamerica.loc.gov/lccn/sn94056869/1909-05-08/ed-1.json"}, {"date_issued": "1909-05-15", "url": "http://chroniclingamerica.loc.gov/lccn/sn94056869/1909-05-15/ed-1.json"}, {"date_issued": "1909-05-22", "url": "http://chroniclingamerica.loc.gov/lccn/sn94056869/1909-05-22/ed-1.json"}, {"date_issued": "1909-05-29", "url": "http://chroniclingamerica.loc.gov/lccn/sn94056869/1909-05-29/ed-1.json"}, {"date_issued": "1909-06-05", "url": "http://chroniclingamerica.loc.gov/lccn/sn94056869/1909-06-05/ed-1.json"}, {"date_issued": "1909-06-12", "url": "http://chroniclingamerica.loc.gov/lccn/sn94056869/1909-06-12/ed-1.json"}, {"date_issued": "1909-06-19", "url": "http://chroniclingamerica.loc.gov/lccn/sn94056869/1909-06-19/ed-1.json"}, {"date_issued": "1909-06-26", "url": "http://chroniclingamerica.loc.gov/lccn/sn94056869/1909-06-26/ed-1.json"}, {"date_issued": "1909-07-03", "url": "http://chroniclingamerica.loc.gov/lccn/sn94056869/1909-07-03/ed-1.json"}, {"date_issued": "1909-07-10", "url": "http://chroniclingamerica.loc.gov/lccn/sn94056869/1909-07-10/ed-1.json"}, {"date_issued": "1909-07-17", "url": "http://chroniclingamerica.loc.gov/lccn/sn94056869/1909-07-17/ed-1.json"}, {"date_issued": "1909-07-24", "url": "http://chroniclingamerica.loc.gov/lccn/sn94056869/1909-07-24/ed-1.json"}, {"date_issued": "1909-07-31", "url": "http://chroniclingamerica.loc.gov/lccn/sn94056869/1909-07-31/ed-1.json"}, {"date_issued": "1909-08-07", "url": "http://chroniclingamerica.loc.gov/lccn/sn94056869/1909-08-07/ed-1.json"}, {"date_issued": "1909-08-14", "url": "http://chroniclingamerica.loc.gov/lccn/sn94056869/1909-08-14/ed-1.json"}, {"date_issued": "1909-08-21", "url": "http://chroniclingamerica.loc.gov/lccn/sn94056869/1909-08-21/ed-1.json"}, {"date_issued": "1909-08-28", "url": "http://chroniclingamerica.loc.gov/lccn/sn94056869/1909-08-28/ed-1.json"}, {"date_issued": "1909-09-04", "url": "http://chroniclingamerica.loc.gov/lccn/sn94056869/1909-09-04/ed-1.json"}, {"date_issued": "1909-09-11", "url": "http://chroniclingamerica.loc.gov/lccn/sn94056869/1909-09-11/ed-1.json"}, {"date_issued": "1909-09-18", "url": "http://chroniclingamerica.loc.gov/lccn/sn94056869/1909-09-18/ed-1.json"}, {"date_issued": "1909-09-25", "url": "http://chroniclingamerica.loc.gov/lccn/sn94056869/1909-09-25/ed-1.json"}, {"date_issued": "1909-10-02", "url": "http://chroniclingamerica.loc.gov/lccn/sn94056869/1909-10-02/ed-1.json"}, {"date_issued": "1909-10-09", "url": "http://chroniclingamerica.loc.gov/lccn/sn94056869/1909-10-09/ed-1.json"}, {"date_issued": "1909-10-16", "url": "http://chroniclingamerica.loc.gov/lccn/sn94056869/1909-10-16/ed-1.json"}, {"date_issued": "1909-10-23", "url": "http://chroniclingamerica.loc.gov/lccn/sn94056869/1909-10-23/ed-1.json"}, {"date_issued": "1909-10-30", "url": "http://chroniclingamerica.loc.gov/lccn/sn94056869/1909-10-30/ed-1.json"}, {"date_issued": "1909-11-06", "url": "http://chroniclingamerica.loc.gov/lccn/sn94056869/1909-11-06/ed-1.json"}, {"date_issued": "1909-11-13", "url": "http://chroniclingamerica.loc.gov/lccn/sn94056869/1909-11-13/ed-1.json"}, {"date_issued": "1909-11-20", "url": "http://chroniclingamerica.loc.gov/lccn/sn94056869/1909-11-20/ed-1.json"}, {"date_issued": "1909-11-27", "url": "http://chroniclingamerica.loc.gov/lccn/sn94056869/1909-11-27/ed-1.json"}, {"date_issued": "1909-12-04", "url": "http://chroniclingamerica.loc.gov/lccn/sn94056869/1909-12-04/ed-1.json"}, {"date_issued": "1909-12-11", "url": "http://chroniclingamerica.loc.gov/lccn/sn94056869/1909-12-11/ed-1.json"}, {"date_issued": "1909-12-18", "url": "http://chroniclingamerica.loc.gov/lccn/sn94056869/1909-12-18/ed-1.json"}, {"date_issued": "1909-12-25", "url": "http://chroniclingamerica.loc.gov/lccn/sn94056869/1909-12-25/ed-1.json"}, {"date_issued": "1912-01-13", "url": "http://chroniclingamerica.loc.gov/lccn/sn94056869/1912-01-13/ed-1.json"}, {"date_issued": "1912-01-20", "url": "http://chroniclingamerica.loc.gov/lccn/sn94056869/1912-01-20/ed-1.json"}, {"date_issued": "1912-01-27", "url": "http://chroniclingamerica.loc.gov/lccn/sn94056869/1912-01-27/ed-1.json"}, {"date_issued": "1912-02-03", "url": "http://chroniclingamerica.loc.gov/lccn/sn94056869/1912-02-03/ed-1.json"}, {"date_issued": "1912-02-10", "url": "http://chroniclingamerica.loc.gov/lccn/sn94056869/1912-02-10/ed-1.json"}, {"date_issued": "1912-02-17", "url": "http://chroniclingamerica.loc.gov/lccn/sn94056869/1912-02-17/ed-1.json"}, {"date_issued": "1912-02-24", "url": "http://chroniclingamerica.loc.gov/lccn/sn94056869/1912-02-24/ed-1.json"}, {"date_issued": "1912-03-02", "url": "http://chroniclingamerica.loc.gov/lccn/sn94056869/1912-03-02/ed-1.json"}, {"date_issued": "1912-03-09", "url": "http://chroniclingamerica.loc.gov/lccn/sn94056869/1912-03-09/ed-1.json"}, {"date_issued": "1912-03-16", "url": "http://chroniclingamerica.loc.gov/lccn/sn94056869/1912-03-16/ed-1.json"}, {"date_issued": "1912-03-23", "url": "http://chroniclingamerica.loc.gov/lccn/sn94056869/1912-03-23/ed-1.json"}, {"date_issued": "1912-03-30", "url": "http://chroniclingamerica.loc.gov/lccn/sn94056869/1912-03-30/ed-1.json"}, {"date_issued": "1912-04-06", "url": "http://chroniclingamerica.loc.gov/lccn/sn94056869/1912-04-06/ed-1.json"}, {"date_issued": "1912-04-13", "url": "http://chroniclingamerica.loc.gov/lccn/sn94056869/1912-04-13/ed-1.json"}, {"date_issued": "1912-04-20", "url": "http://chroniclingamerica.loc.gov/lccn/sn94056869/1912-04-20/ed-1.json"}, {"date_issued": "1912-04-27", "url": "http://chroniclingamerica.loc.gov/lccn/sn94056869/1912-04-27/ed-1.json"}, {"date_issued": "1912-05-04", "url": "http://chroniclingamerica.loc.gov/lccn/sn94056869/1912-05-04/ed-1.json"}, {"date_issued": "1912-05-11", "url": "http://chroniclingamerica.loc.gov/lccn/sn94056869/1912-05-11/ed-1.json"}, {"date_issued": "1912-05-18", "url": "http://chroniclingamerica.loc.gov/lccn/sn94056869/1912-05-18/ed-1.json"}, {"date_issued": "1912-05-25", "url": "http://chroniclingamerica.loc.gov/lccn/sn94056869/1912-05-25/ed-1.json"}, {"date_issued": "1912-06-01", "url": "http://chroniclingamerica.loc.gov/lccn/sn94056869/1912-06-01/ed-1.json"}, {"date_issued": "1912-06-08", "url": "http://chroniclingamerica.loc.gov/lccn/sn94056869/1912-06-08/ed-1.json"}, {"date_issued": "1912-06-15", "url": "http://chroniclingamerica.loc.gov/lccn/sn94056869/1912-06-15/ed-1.json"}, {"date_issued": "1912-06-22", "url": "http://chroniclingamerica.loc.gov/lccn/sn94056869/1912-06-22/ed-1.json"}, {"date_issued": "1912-06-29", "url": "http://chroniclingamerica.loc.gov/lccn/sn94056869/1912-06-29/ed-1.json"}, {"date_issued": "1912-07-06", "url": "http://chroniclingamerica.loc.gov/lccn/sn94056869/1912-07-06/ed-1.json"}, {"date_issued": "1912-07-13", "url": "http://chroniclingamerica.loc.gov/lccn/sn94056869/1912-07-13/ed-1.json"}, {"date_issued": "1912-07-20", "url": "http://chroniclingamerica.loc.gov/lccn/sn94056869/1912-07-20/ed-1.json"}, {"date_issued": "1912-07-27", "url": "http://chroniclingamerica.loc.gov/lccn/sn94056869/1912-07-27/ed-1.json"}, {"date_issued": "1912-08-03", "url": "http://chroniclingamerica.loc.gov/lccn/sn94056869/1912-08-03/ed-1.json"}, {"date_issued": "1912-08-10", "url": "http://chroniclingamerica.loc.gov/lccn/sn94056869/1912-08-10/ed-1.json"}, {"date_issued": "1912-08-17", "url": "http://chroniclingamerica.loc.gov/lccn/sn94056869/1912-08-17/ed-1.json"}, {"date_issued": "1912-08-24", "url": "http://chroniclingamerica.loc.gov/lccn/sn94056869/1912-08-24/ed-1.json"}, {"date_issued": "1912-08-31", "url": "http://chroniclingamerica.loc.gov/lccn/sn94056869/1912-08-31/ed-1.json"}, {"date_issued": "1912-09-07", "url": "http://chroniclingamerica.loc.gov/lccn/sn94056869/1912-09-07/ed-1.json"}, {"date_issued": "1912-09-14", "url": "http://chroniclingamerica.loc.gov/lccn/sn94056869/1912-09-14/ed-1.json"}, {"date_issued": "1912-09-21", "url": "http://chroniclingamerica.loc.gov/lccn/sn94056869/1912-09-21/ed-1.json"}, {"date_issued": "1912-09-28", "url": "http://chroniclingamerica.loc.gov/lccn/sn94056869/1912-09-28/ed-1.json"}, {"date_issued": "1912-10-05", "url": "http://chroniclingamerica.loc.gov/lccn/sn94056869/1912-10-05/ed-1.json"}, {"date_issued": "1912-10-12", "url": "http://chroniclingamerica.loc.gov/lccn/sn94056869/1912-10-12/ed-1.json"}, {"date_issued": "1912-10-19", "url": "http://chroniclingamerica.loc.gov/lccn/sn94056869/1912-10-19/ed-1.json"}, {"date_issued": "1912-10-26", "url": "http://chroniclingamerica.loc.gov/lccn/sn94056869/1912-10-26/ed-1.json"}, {"date_issued": "1912-11-02", "url": "http://chroniclingamerica.loc.gov/lccn/sn94056869/1912-11-02/ed-1.json"}, {"date_issued": "1912-11-09", "url": "http://chroniclingamerica.loc.gov/lccn/sn94056869/1912-11-09/ed-1.json"}, {"date_issued": "1912-11-16", "url": "http://chroniclingamerica.loc.gov/lccn/sn94056869/1912-11-16/ed-1.json"}, {"date_issued": "1912-11-23", "url": "http://chroniclingamerica.loc.gov/lccn/sn94056869/1912-11-23/ed-1.json"}, {"date_issued": "1912-11-30", "url": "http://chroniclingamerica.loc.gov/lccn/sn94056869/1912-11-30/ed-1.json"}, {"date_issued": "1912-12-07", "url": "http://chroniclingamerica.loc.gov/lccn/sn94056869/1912-12-07/ed-1.json"}, {"date_issued": "1912-12-14", "url": "http://chroniclingamerica.loc.gov/lccn/sn94056869/1912-12-14/ed-1.json"}, {"date_issued": "1912-12-21", "url": "http://chroniclingamerica.loc.gov/lccn/sn94056869/1912-12-21/ed-1.json"}, {"date_issued": "1912-12-28", "url": "http://chroniclingamerica.loc.gov/lccn/sn94056869/1912-12-28/ed-1.json"}, {"date_issued": "1913-01-04", "url": "http://chroniclingamerica.loc.gov/lccn/sn94056869/1913-01-04/ed-1.json"}, {"date_issued": "1913-01-11", "url": "http://chroniclingamerica.loc.gov/lccn/sn94056869/1913-01-11/ed-1.json"}, {"date_issued": "1913-01-18", "url": "http://chroniclingamerica.loc.gov/lccn/sn94056869/1913-01-18/ed-1.json"}, {"date_issued": "1913-01-25", "url": "http://chroniclingamerica.loc.gov/lccn/sn94056869/1913-01-25/ed-1.json"}, {"date_issued": "1913-02-01", "url": "http://chroniclingamerica.loc.gov/lccn/sn94056869/1913-02-01/ed-1.json"}, {"date_issued": "1913-02-08", "url": "http://chroniclingamerica.loc.gov/lccn/sn94056869/1913-02-08/ed-1.json"}, {"date_issued": "1913-02-15", "url": "http://chroniclingamerica.loc.gov/lccn/sn94056869/1913-02-15/ed-1.json"}, {"date_issued": "1913-02-22", "url": "http://chroniclingamerica.loc.gov/lccn/sn94056869/1913-02-22/ed-1.json"}, {"date_issued": "1913-03-01", "url": "http://chroniclingamerica.loc.gov/lccn/sn94056869/1913-03-01/ed-1.json"}, {"date_issued": "1913-03-08", "url": "http://chroniclingamerica.loc.gov/lccn/sn94056869/1913-03-08/ed-1.json"}, {"date_issued": "1913-03-15", "url": "http://chroniclingamerica.loc.gov/lccn/sn94056869/1913-03-15/ed-1.json"}, {"date_issued": "1913-03-22", "url": "http://chroniclingamerica.loc.gov/lccn/sn94056869/1913-03-22/ed-1.json"}, {"date_issued": "1913-03-29", "url": "http://chroniclingamerica.loc.gov/lccn/sn94056869/1913-03-29/ed-1.json"}, {"date_issued": "1913-04-05", "url": "http://chroniclingamerica.loc.gov/lccn/sn94056869/1913-04-05/ed-1.json"}, {"date_issued": "1913-04-10", "url": "http://chroniclingamerica.loc.gov/lccn/sn94056869/1913-04-10/ed-1.json"}, {"date_issued": "1913-04-17", "url": "http://chroniclingamerica.loc.gov/lccn/sn94056869/1913-04-17/ed-1.json"}, {"date_issued": "1913-04-24", "url": "http://chroniclingamerica.loc.gov/lccn/sn94056869/1913-04-24/ed-1.json"}, {"date_issued": "1913-05-01", "url": "http://chroniclingamerica.loc.gov/lccn/sn94056869/1913-05-01/ed-1.json"}, {"date_issued": "1913-05-08", "url": "http://chroniclingamerica.loc.gov/lccn/sn94056869/1913-05-08/ed-1.json"}, {"date_issued": "1913-05-15", "url": "http://chroniclingamerica.loc.gov/lccn/sn94056869/1913-05-15/ed-1.json"}, {"date_issued": "1913-05-22", "url": "http://chroniclingamerica.loc.gov/lccn/sn94056869/1913-05-22/ed-1.json"}, {"date_issued": "1913-05-29", "url": "http://chroniclingamerica.loc.gov/lccn/sn94056869/1913-05-29/ed-1.json"}, {"date_issued": "1913-06-05", "url": "http://chroniclingamerica.loc.gov/lccn/sn94056869/1913-06-05/ed-1.json"}, {"date_issued": "1913-06-12", "url": "http://chroniclingamerica.loc.gov/lccn/sn94056869/1913-06-12/ed-1.json"}, {"date_issued": "1913-06-19", "url": "http://chroniclingamerica.loc.gov/lccn/sn94056869/1913-06-19/ed-1.json"}, {"date_issued": "1913-06-26", "url": "http://chroniclingamerica.loc.gov/lccn/sn94056869/1913-06-26/ed-1.json"}, {"date_issued": "1913-07-03", "url": "http://chroniclingamerica.loc.gov/lccn/sn94056869/1913-07-03/ed-1.json"}, {"date_issued": "1913-07-17", "url": "http://chroniclingamerica.loc.gov/lccn/sn94056869/1913-07-17/ed-1.json"}, {"date_issued": "1913-07-24", "url": "http://chroniclingamerica.loc.gov/lccn/sn94056869/1913-07-24/ed-1.json"}, {"date_issued": "1913-07-31", "url": "http://chroniclingamerica.loc.gov/lccn/sn94056869/1913-07-31/ed-1.json"}, {"date_issued": "1913-08-07", "url": "http://chroniclingamerica.loc.gov/lccn/sn94056869/1913-08-07/ed-1.json"}, {"date_issued": "1913-08-14", "url": "http://chroniclingamerica.loc.gov/lccn/sn94056869/1913-08-14/ed-1.json"}, {"date_issued": "1913-08-21", "url": "http://chroniclingamerica.loc.gov/lccn/sn94056869/1913-08-21/ed-1.json"}, {"date_issued": "1913-08-28", "url": "http://chroniclingamerica.loc.gov/lccn/sn94056869/1913-08-28/ed-1.json"}, {"date_issued": "1913-09-04", "url": "http://chroniclingamerica.loc.gov/lccn/sn94056869/1913-09-04/ed-1.json"}, {"date_issued": "1913-09-11", "url": "http://chroniclingamerica.loc.gov/lccn/sn94056869/1913-09-11/ed-1.json"}, {"date_issued": "1913-09-18", "url": "http://chroniclingamerica.loc.gov/lccn/sn94056869/1913-09-18/ed-1.json"}, {"date_issued": "1913-09-25", "url": "http://chroniclingamerica.loc.gov/lccn/sn94056869/1913-09-25/ed-1.json"}, {"date_issued": "1913-10-09", "url": "http://chroniclingamerica.loc.gov/lccn/sn94056869/1913-10-09/ed-1.json"}, {"date_issued": "1913-10-16", "url": "http://chroniclingamerica.loc.gov/lccn/sn94056869/1913-10-16/ed-1.json"}, {"date_issued": "1913-10-23", "url": "http://chroniclingamerica.loc.gov/lccn/sn94056869/1913-10-23/ed-1.json"}, {"date_issued": "1913-10-30", "url": "http://chroniclingamerica.loc.gov/lccn/sn94056869/1913-10-30/ed-1.json"}, {"date_issued": "1913-11-06", "url": "http://chroniclingamerica.loc.gov/lccn/sn94056869/1913-11-06/ed-1.json"}, {"date_issued": "1913-11-13", "url": "http://chroniclingamerica.loc.gov/lccn/sn94056869/1913-11-13/ed-1.json"}, {"date_issued": "1913-11-20", "url": "http://chroniclingamerica.loc.gov/lccn/sn94056869/1913-11-20/ed-1.json"}, {"date_issued": "1913-11-27", "url": "http://chroniclingamerica.loc.gov/lccn/sn94056869/1913-11-27/ed-1.json"}, {"date_issued": "1913-12-04", "url": "http://chroniclingamerica.loc.gov/lccn/sn94056869/1913-12-04/ed-1.json"}, {"date_issued": "1913-12-11", "url": "http://chroniclingamerica.loc.gov/lccn/sn94056869/1913-12-11/ed-1.json"}, {"date_issued": "1913-12-18", "url": "http://chroniclingamerica.loc.gov/lccn/sn94056869/1913-12-18/ed-1.json"}, {"date_issued": "1913-12-25", "url": "http://chroniclingamerica.loc.gov/lccn/sn94056869/1913-12-25/ed-1.json"}, {"date_issued": "1914-01-01", "url": "http://chroniclingamerica.loc.gov/lccn/sn94056869/1914-01-01/ed-1.json"}, {"date_issued": "1914-01-08", "url": "http://chroniclingamerica.loc.gov/lccn/sn94056869/1914-01-08/ed-1.json"}, {"date_issued": "1914-01-15", "url": "http://chroniclingamerica.loc.gov/lccn/sn94056869/1914-01-15/ed-1.json"}, {"date_issued": "1914-01-29", "url": "http://chroniclingamerica.loc.gov/lccn/sn94056869/1914-01-29/ed-1.json"}, {"date_issued": "1914-02-05", "url": "http://chroniclingamerica.loc.gov/lccn/sn94056869/1914-02-05/ed-1.json"}, {"date_issued": "1914-02-12", "url": "http://chroniclingamerica.loc.gov/lccn/sn94056869/1914-02-12/ed-1.json"}, {"date_issued": "1914-02-19", "url": "http://chroniclingamerica.loc.gov/lccn/sn94056869/1914-02-19/ed-1.json"}, {"date_issued": "1914-02-26", "url": "http://chroniclingamerica.loc.gov/lccn/sn94056869/1914-02-26/ed-1.json"}, {"date_issued": "1914-03-05", "url": "http://chroniclingamerica.loc.gov/lccn/sn94056869/1914-03-05/ed-1.json"}, {"date_issued": "1914-03-12", "url": "http://chroniclingamerica.loc.gov/lccn/sn94056869/1914-03-12/ed-1.json"}, {"date_issued": "1914-03-19", "url": "http://chroniclingamerica.loc.gov/lccn/sn94056869/1914-03-19/ed-1.json"}, {"date_issued": "1914-03-26", "url": "http://chroniclingamerica.loc.gov/lccn/sn94056869/1914-03-26/ed-1.json"}, {"date_issued": "1914-04-02", "url": "http://chroniclingamerica.loc.gov/lccn/sn94056869/1914-04-02/ed-1.json"}, {"date_issued": "1914-04-06", "url": "http://chroniclingamerica.loc.gov/lccn/sn94056869/1914-04-06/ed-1.json"}, {"date_issued": "1914-04-09", "url": "http://chroniclingamerica.loc.gov/lccn/sn94056869/1914-04-09/ed-1.json"}, {"date_issued": "1914-04-16", "url": "http://chroniclingamerica.loc.gov/lccn/sn94056869/1914-04-16/ed-1.json"}, {"date_issued": "1914-04-23", "url": "http://chroniclingamerica.loc.gov/lccn/sn94056869/1914-04-23/ed-1.json"}, {"date_issued": "1914-04-30", "url": "http://chroniclingamerica.loc.gov/lccn/sn94056869/1914-04-30/ed-1.json"}, {"date_issued": "1914-05-07", "url": "http://chroniclingamerica.loc.gov/lccn/sn94056869/1914-05-07/ed-1.json"}, {"date_issued": "1914-05-14", "url": "http://chroniclingamerica.loc.gov/lccn/sn94056869/1914-05-14/ed-1.json"}, {"date_issued": "1914-05-21", "url": "http://chroniclingamerica.loc.gov/lccn/sn94056869/1914-05-21/ed-1.json"}, {"date_issued": "1914-05-28", "url": "http://chroniclingamerica.loc.gov/lccn/sn94056869/1914-05-28/ed-1.json"}, {"date_issued": "1914-06-04", "url": "http://chroniclingamerica.loc.gov/lccn/sn94056869/1914-06-04/ed-1.json"}, {"date_issued": "1914-06-11", "url": "http://chroniclingamerica.loc.gov/lccn/sn94056869/1914-06-11/ed-1.json"}, {"date_issued": "1914-06-18", "url": "http://chroniclingamerica.loc.gov/lccn/sn94056869/1914-06-18/ed-1.json"}, {"date_issued": "1914-06-25", "url": "http://chroniclingamerica.loc.gov/lccn/sn94056869/1914-06-25/ed-1.json"}, {"date_issued": "1914-07-02", "url": "http://chroniclingamerica.loc.gov/lccn/sn94056869/1914-07-02/ed-1.json"}, {"date_issued": "1914-07-09", "url": "http://chroniclingamerica.loc.gov/lccn/sn94056869/1914-07-09/ed-1.json"}, {"date_issued": "1914-07-16", "url": "http://chroniclingamerica.loc.gov/lccn/sn94056869/1914-07-16/ed-1.json"}, {"date_issued": "1914-07-23", "url": "http://chroniclingamerica.loc.gov/lccn/sn94056869/1914-07-23/ed-1.json"}, {"date_issued": "1914-07-30", "url": "http://chroniclingamerica.loc.gov/lccn/sn94056869/1914-07-30/ed-1.json"}, {"date_issued": "1914-08-06", "url": "http://chroniclingamerica.loc.gov/lccn/sn94056869/1914-08-06/ed-1.json"}, {"date_issued": "1914-08-13", "url": "http://chroniclingamerica.loc.gov/lccn/sn94056869/1914-08-13/ed-1.json"}, {"date_issued": "1914-08-20", "url": "http://chroniclingamerica.loc.gov/lccn/sn94056869/1914-08-20/ed-1.json"}, {"date_issued": "1914-08-27", "url": "http://chroniclingamerica.loc.gov/lccn/sn94056869/1914-08-27/ed-1.json"}, {"date_issued": "1914-09-03", "url": "http://chroniclingamerica.loc.gov/lccn/sn94056869/1914-09-03/ed-1.json"}, {"date_issued": "1914-09-17", "url": "http://chroniclingamerica.loc.gov/lccn/sn94056869/1914-09-17/ed-1.json"}, {"date_issued": "1914-09-24", "url": "http://chroniclingamerica.loc.gov/lccn/sn94056869/1914-09-24/ed-1.json"}, {"date_issued": "1914-10-01", "url": "http://chroniclingamerica.loc.gov/lccn/sn94056869/1914-10-01/ed-1.json"}, {"date_issued": "1914-10-08", "url": "http://chroniclingamerica.loc.gov/lccn/sn94056869/1914-10-08/ed-1.json"}, {"date_issued": "1914-10-15", "url": "http://chroniclingamerica.loc.gov/lccn/sn94056869/1914-10-15/ed-1.json"}, {"date_issued": "1914-10-22", "url": "http://chroniclingamerica.loc.gov/lccn/sn94056869/1914-10-22/ed-1.json"}, {"date_issued": "1914-10-29", "url": "http://chroniclingamerica.loc.gov/lccn/sn94056869/1914-10-29/ed-1.json"}, {"date_issued": "1914-11-05", "url": "http://chroniclingamerica.loc.gov/lccn/sn94056869/1914-11-05/ed-1.json"}, {"date_issued": "1914-11-12", "url": "http://chroniclingamerica.loc.gov/lccn/sn94056869/1914-11-12/ed-1.json"}, {"date_issued": "1914-11-19", "url": "http://chroniclingamerica.loc.gov/lccn/sn94056869/1914-11-19/ed-1.json"}, {"date_issued": "1914-11-26", "url": "http://chroniclingamerica.loc.gov/lccn/sn94056869/1914-11-26/ed-1.json"}, {"date_issued": "1914-12-03", "url": "http://chroniclingamerica.loc.gov/lccn/sn94056869/1914-12-03/ed-1.json"}, {"date_issued": "1914-12-10", "url": "http://chroniclingamerica.loc.gov/lccn/sn94056869/1914-12-10/ed-1.json"}, {"date_issued": "1914-12-17", "url": "http://chroniclingamerica.loc.gov/lccn/sn94056869/1914-12-17/ed-1.json"}, {"date_issued": "1914-12-24", "url": "http://chroniclingamerica.loc.gov/lccn/sn94056869/1914-12-24/ed-1.json"}, {"date_issued": "1916-01-06", "url": "http://chroniclingamerica.loc.gov/lccn/sn94056869/1916-01-06/ed-1.json"}, {"date_issued": "1916-01-13", "url": "http://chroniclingamerica.loc.gov/lccn/sn94056869/1916-01-13/ed-1.json"}, {"date_issued": "1916-01-20", "url": "http://chroniclingamerica.loc.gov/lccn/sn94056869/1916-01-20/ed-1.json"}, {"date_issued": "1916-01-27", "url": "http://chroniclingamerica.loc.gov/lccn/sn94056869/1916-01-27/ed-1.json"}, {"date_issued": "1916-02-03", "url": "http://chroniclingamerica.loc.gov/lccn/sn94056869/1916-02-03/ed-1.json"}, {"date_issued": "1916-02-10", "url": "http://chroniclingamerica.loc.gov/lccn/sn94056869/1916-02-10/ed-1.json"}, {"date_issued": "1916-02-17", "url": "http://chroniclingamerica.loc.gov/lccn/sn94056869/1916-02-17/ed-1.json"}, {"date_issued": "1916-02-24", "url": "http://chroniclingamerica.loc.gov/lccn/sn94056869/1916-02-24/ed-1.json"}, {"date_issued": "1916-03-02", "url": "http://chroniclingamerica.loc.gov/lccn/sn94056869/1916-03-02/ed-1.json"}, {"date_issued": "1916-03-09", "url": "http://chroniclingamerica.loc.gov/lccn/sn94056869/1916-03-09/ed-1.json"}, {"date_issued": "1916-03-16", "url": "http://chroniclingamerica.loc.gov/lccn/sn94056869/1916-03-16/ed-1.json"}, {"date_issued": "1916-03-23", "url": "http://chroniclingamerica.loc.gov/lccn/sn94056869/1916-03-23/ed-1.json"}, {"date_issued": "1916-03-30", "url": "http://chroniclingamerica.loc.gov/lccn/sn94056869/1916-03-30/ed-1.json"}, {"date_issued": "1916-04-06", "url": "http://chroniclingamerica.loc.gov/lccn/sn94056869/1916-04-06/ed-1.json"}, {"date_issued": "1916-04-13", "url": "http://chroniclingamerica.loc.gov/lccn/sn94056869/1916-04-13/ed-1.json"}, {"date_issued": "1916-04-20", "url": "http://chroniclingamerica.loc.gov/lccn/sn94056869/1916-04-20/ed-1.json"}, {"date_issued": "1916-04-27", "url": "http://chroniclingamerica.loc.gov/lccn/sn94056869/1916-04-27/ed-1.json"}, {"date_issued": "1916-05-04", "url": "http://chroniclingamerica.loc.gov/lccn/sn94056869/1916-05-04/ed-1.json"}, {"date_issued": "1916-05-11", "url": "http://chroniclingamerica.loc.gov/lccn/sn94056869/1916-05-11/ed-1.json"}, {"date_issued": "1916-05-18", "url": "http://chroniclingamerica.loc.gov/lccn/sn94056869/1916-05-18/ed-1.json"}, {"date_issued": "1916-05-25", "url": "http://chroniclingamerica.loc.gov/lccn/sn94056869/1916-05-25/ed-1.json"}, {"date_issued": "1916-06-01", "url": "http://chroniclingamerica.loc.gov/lccn/sn94056869/1916-06-01/ed-1.json"}, {"date_issued": "1916-06-08", "url": "http://chroniclingamerica.loc.gov/lccn/sn94056869/1916-06-08/ed-1.json"}, {"date_issued": "1916-06-15", "url": "http://chroniclingamerica.loc.gov/lccn/sn94056869/1916-06-15/ed-1.json"}, {"date_issued": "1916-06-22", "url": "http://chroniclingamerica.loc.gov/lccn/sn94056869/1916-06-22/ed-1.json"}, {"date_issued": "1916-06-29", "url": "http://chroniclingamerica.loc.gov/lccn/sn94056869/1916-06-29/ed-1.json"}, {"date_issued": "1916-07-06", "url": "http://chroniclingamerica.loc.gov/lccn/sn94056869/1916-07-06/ed-1.json"}, {"date_issued": "1916-07-13", "url": "http://chroniclingamerica.loc.gov/lccn/sn94056869/1916-07-13/ed-1.json"}, {"date_issued": "1916-07-20", "url": "http://chroniclingamerica.loc.gov/lccn/sn94056869/1916-07-20/ed-1.json"}, {"date_issued": "1916-07-27", "url": "http://chroniclingamerica.loc.gov/lccn/sn94056869/1916-07-27/ed-1.json"}, {"date_issued": "1916-08-03", "url": "http://chroniclingamerica.loc.gov/lccn/sn94056869/1916-08-03/ed-1.json"}, {"date_issued": "1916-08-10", "url": "http://chroniclingamerica.loc.gov/lccn/sn94056869/1916-08-10/ed-1.json"}, {"date_issued": "1916-08-17", "url": "http://chroniclingamerica.loc.gov/lccn/sn94056869/1916-08-17/ed-1.json"}, {"date_issued": "1916-08-24", "url": "http://chroniclingamerica.loc.gov/lccn/sn94056869/1916-08-24/ed-1.json"}, {"date_issued": "1916-08-31", "url": "http://chroniclingamerica.loc.gov/lccn/sn94056869/1916-08-31/ed-1.json"}, {"date_issued": "1916-09-07", "url": "http://chroniclingamerica.loc.gov/lccn/sn94056869/1916-09-07/ed-1.json"}, {"date_issued": "1916-09-14", "url": "http://chroniclingamerica.loc.gov/lccn/sn94056869/1916-09-14/ed-1.json"}, {"date_issued": "1916-09-21", "url": "http://chroniclingamerica.loc.gov/lccn/sn94056869/1916-09-21/ed-1.json"}, {"date_issued": "1916-09-28", "url": "http://chroniclingamerica.loc.gov/lccn/sn94056869/1916-09-28/ed-1.json"}, {"date_issued": "1916-10-05", "url": "http://chroniclingamerica.loc.gov/lccn/sn94056869/1916-10-05/ed-1.json"}, {"date_issued": "1916-10-12", "url": "http://chroniclingamerica.loc.gov/lccn/sn94056869/1916-10-12/ed-1.json"}, {"date_issued": "1916-10-19", "url": "http://chroniclingamerica.loc.gov/lccn/sn94056869/1916-10-19/ed-1.json"}, {"date_issued": "1916-10-26", "url": "http://chroniclingamerica.loc.gov/lccn/sn94056869/1916-10-26/ed-1.json"}, {"date_issued": "1916-11-02", "url": "http://chroniclingamerica.loc.gov/lccn/sn94056869/1916-11-02/ed-1.json"}, {"date_issued": "1916-11-09", "url": "http://chroniclingamerica.loc.gov/lccn/sn94056869/1916-11-09/ed-1.json"}, {"date_issued": "1916-11-16", "url": "http://chroniclingamerica.loc.gov/lccn/sn94056869/1916-11-16/ed-1.json"}, {"date_issued": "1916-11-23", "url": "http://chroniclingamerica.loc.gov/lccn/sn94056869/1916-11-23/ed-1.json"}, {"date_issued": "1916-11-30", "url": "http://chroniclingamerica.loc.gov/lccn/sn94056869/1916-11-30/ed-1.json"}, {"date_issued": "1916-12-07", "url": "http://chroniclingamerica.loc.gov/lccn/sn94056869/1916-12-07/ed-1.json"}, {"date_issued": "1916-12-14", "url": "http://chroniclingamerica.loc.gov/lccn/sn94056869/1916-12-14/ed-1.json"}, {"date_issued": "1916-12-21", "url": "http://chroniclingamerica.loc.gov/lccn/sn94056869/1916-12-21/ed-1.json"}, {"date_issued": "1916-12-28", "url": "http://chroniclingamerica.loc.gov/lccn/sn94056869/1916-12-28/ed-1.json"}, {"date_issued": "1917-01-04", "url": "http://chroniclingamerica.loc.gov/lccn/sn94056869/1917-01-04/ed-1.json"}, {"date_issued": "1917-01-11", "url": "http://chroniclingamerica.loc.gov/lccn/sn94056869/1917-01-11/ed-1.json"}, {"date_issued": "1917-01-18", "url": "http://chroniclingamerica.loc.gov/lccn/sn94056869/1917-01-18/ed-1.json"}, {"date_issued": "1917-01-25", "url": "http://chroniclingamerica.loc.gov/lccn/sn94056869/1917-01-25/ed-1.json"}, {"date_issued": "1917-02-01", "url": "http://chroniclingamerica.loc.gov/lccn/sn94056869/1917-02-01/ed-1.json"}, {"date_issued": "1917-02-08", "url": "http://chroniclingamerica.loc.gov/lccn/sn94056869/1917-02-08/ed-1.json"}, {"date_issued": "1917-02-15", "url": "http://chroniclingamerica.loc.gov/lccn/sn94056869/1917-02-15/ed-1.json"}, {"date_issued": "1917-02-22", "url": "http://chroniclingamerica.loc.gov/lccn/sn94056869/1917-02-22/ed-1.json"}, {"date_issued": "1917-03-01", "url": "http://chroniclingamerica.loc.gov/lccn/sn94056869/1917-03-01/ed-1.json"}, {"date_issued": "1917-03-08", "url": "http://chroniclingamerica.loc.gov/lccn/sn94056869/1917-03-08/ed-1.json"}, {"date_issued": "1917-03-15", "url": "http://chroniclingamerica.loc.gov/lccn/sn94056869/1917-03-15/ed-1.json"}, {"date_issued": "1917-03-22", "url": "http://chroniclingamerica.loc.gov/lccn/sn94056869/1917-03-22/ed-1.json"}, {"date_issued": "1917-03-29", "url": "http://chroniclingamerica.loc.gov/lccn/sn94056869/1917-03-29/ed-1.json"}, {"date_issued": "1917-04-05", "url": "http://chroniclingamerica.loc.gov/lccn/sn94056869/1917-04-05/ed-1.json"}, {"date_issued": "1917-04-12", "url": "http://chroniclingamerica.loc.gov/lccn/sn94056869/1917-04-12/ed-1.json"}, {"date_issued": "1917-04-19", "url": "http://chroniclingamerica.loc.gov/lccn/sn94056869/1917-04-19/ed-1.json"}, {"date_issued": "1917-04-26", "url": "http://chroniclingamerica.loc.gov/lccn/sn94056869/1917-04-26/ed-1.json"}, {"date_issued": "1917-05-03", "url": "http://chroniclingamerica.loc.gov/lccn/sn94056869/1917-05-03/ed-1.json"}, {"date_issued": "1917-05-10", "url": "http://chroniclingamerica.loc.gov/lccn/sn94056869/1917-05-10/ed-1.json"}, {"date_issued": "1917-05-17", "url": "http://chroniclingamerica.loc.gov/lccn/sn94056869/1917-05-17/ed-1.json"}, {"date_issued": "1917-05-24", "url": "http://chroniclingamerica.loc.gov/lccn/sn94056869/1917-05-24/ed-1.json"}, {"date_issued": "1917-05-31", "url": "http://chroniclingamerica.loc.gov/lccn/sn94056869/1917-05-31/ed-1.json"}, {"date_issued": "1917-06-07", "url": "http://chroniclingamerica.loc.gov/lccn/sn94056869/1917-06-07/ed-1.json"}, {"date_issued": "1917-06-14", "url": "http://chroniclingamerica.loc.gov/lccn/sn94056869/1917-06-14/ed-1.json"}, {"date_issued": "1917-06-21", "url": "http://chroniclingamerica.loc.gov/lccn/sn94056869/1917-06-21/ed-1.json"}, {"date_issued": "1917-06-28", "url": "http://chroniclingamerica.loc.gov/lccn/sn94056869/1917-06-28/ed-1.json"}, {"date_issued": "1917-07-05", "url": "http://chroniclingamerica.loc.gov/lccn/sn94056869/1917-07-05/ed-1.json"}, {"date_issued": "1917-07-12", "url": "http://chroniclingamerica.loc.gov/lccn/sn94056869/1917-07-12/ed-1.json"}, {"date_issued": "1917-07-19", "url": "http://chroniclingamerica.loc.gov/lccn/sn94056869/1917-07-19/ed-1.json"}, {"date_issued": "1917-07-26", "url": "http://chroniclingamerica.loc.gov/lccn/sn94056869/1917-07-26/ed-1.json"}, {"date_issued": "1917-08-02", "url": "http://chroniclingamerica.loc.gov/lccn/sn94056869/1917-08-02/ed-1.json"}, {"date_issued": "1917-08-09", "url": "http://chroniclingamerica.loc.gov/lccn/sn94056869/1917-08-09/ed-1.json"}, {"date_issued": "1917-08-16", "url": "http://chroniclingamerica.loc.gov/lccn/sn94056869/1917-08-16/ed-1.json"}, {"date_issued": "1917-08-23", "url": "http://chroniclingamerica.loc.gov/lccn/sn94056869/1917-08-23/ed-1.json"}, {"date_issued": "1917-08-30", "url": "http://chroniclingamerica.loc.gov/lccn/sn94056869/1917-08-30/ed-1.json"}, {"date_issued": "1917-09-06", "url": "http://chroniclingamerica.loc.gov/lccn/sn94056869/1917-09-06/ed-1.json"}, {"date_issued": "1917-09-13", "url": "http://chroniclingamerica.loc.gov/lccn/sn94056869/1917-09-13/ed-1.json"}, {"date_issued": "1917-09-27", "url": "http://chroniclingamerica.loc.gov/lccn/sn94056869/1917-09-27/ed-1.json"}, {"date_issued": "1917-10-04", "url": "http://chroniclingamerica.loc.gov/lccn/sn94056869/1917-10-04/ed-1.json"}, {"date_issued": "1917-10-11", "url": "http://chroniclingamerica.loc.gov/lccn/sn94056869/1917-10-11/ed-1.json"}, {"date_issued": "1917-10-18", "url": "http://chroniclingamerica.loc.gov/lccn/sn94056869/1917-10-18/ed-1.json"}, {"date_issued": "1917-10-25", "url": "http://chroniclingamerica.loc.gov/lccn/sn94056869/1917-10-25/ed-1.json"}, {"date_issued": "1917-11-01", "url": "http://chroniclingamerica.loc.gov/lccn/sn94056869/1917-11-01/ed-1.json"}, {"date_issued": "1917-11-08", "url": "http://chroniclingamerica.loc.gov/lccn/sn94056869/1917-11-08/ed-1.json"}, {"date_issued": "1917-11-15", "url": "http://chroniclingamerica.loc.gov/lccn/sn94056869/1917-11-15/ed-1.json"}, {"date_issued": "1917-11-22", "url": "http://chroniclingamerica.loc.gov/lccn/sn94056869/1917-11-22/ed-1.json"}, {"date_issued": "1917-11-29", "url": "http://chroniclingamerica.loc.gov/lccn/sn94056869/1917-11-29/ed-1.json"}, {"date_issued": "1917-12-06", "url": "http://chroniclingamerica.loc.gov/lccn/sn94056869/1917-12-06/ed-1.json"}, {"date_issued": "1917-12-13", "url": "http://chroniclingamerica.loc.gov/lccn/sn94056869/1917-12-13/ed-1.json"}, {"date_issued": "1917-12-20", "url": "http://chroniclingamerica.loc.gov/lccn/sn94056869/1917-12-20/ed-1.json"}, {"date_issued": "1917-12-27", "url": "http://chroniclingamerica.loc.gov/lccn/sn94056869/1917-12-27/ed-1.json"}, {"date_issued": "1918-01-03", "url": "http://chroniclingamerica.loc.gov/lccn/sn94056869/1918-01-03/ed-1.json"}, {"date_issued": "1918-01-10", "url": "http://chroniclingamerica.loc.gov/lccn/sn94056869/1918-01-10/ed-1.json"}, {"date_issued": "1918-01-17", "url": "http://chroniclingamerica.loc.gov/lccn/sn94056869/1918-01-17/ed-1.json"}, {"date_issued": "1918-01-24", "url": "http://chroniclingamerica.loc.gov/lccn/sn94056869/1918-01-24/ed-1.json"}, {"date_issued": "1918-01-31", "url": "http://chroniclingamerica.loc.gov/lccn/sn94056869/1918-01-31/ed-1.json"}, {"date_issued": "1918-02-07", "url": "http://chroniclingamerica.loc.gov/lccn/sn94056869/1918-02-07/ed-1.json"}, {"date_issued": "1918-02-14", "url": "http://chroniclingamerica.loc.gov/lccn/sn94056869/1918-02-14/ed-1.json"}, {"date_issued": "1918-02-21", "url": "http://chroniclingamerica.loc.gov/lccn/sn94056869/1918-02-21/ed-1.json"}, {"date_issued": "1918-02-28", "url": "http://chroniclingamerica.loc.gov/lccn/sn94056869/1918-02-28/ed-1.json"}, {"date_issued": "1918-03-07", "url": "http://chroniclingamerica.loc.gov/lccn/sn94056869/1918-03-07/ed-1.json"}, {"date_issued": "1918-03-14", "url": "http://chroniclingamerica.loc.gov/lccn/sn94056869/1918-03-14/ed-1.json"}, {"date_issued": "1918-03-21", "url": "http://chroniclingamerica.loc.gov/lccn/sn94056869/1918-03-21/ed-1.json"}, {"date_issued": "1918-03-28", "url": "http://chroniclingamerica.loc.gov/lccn/sn94056869/1918-03-28/ed-1.json"}, {"date_issued": "1918-04-04", "url": "http://chroniclingamerica.loc.gov/lccn/sn94056869/1918-04-04/ed-1.json"}, {"date_issued": "1918-04-11", "url": "http://chroniclingamerica.loc.gov/lccn/sn94056869/1918-04-11/ed-1.json"}, {"date_issued": "1918-04-18", "url": "http://chroniclingamerica.loc.gov/lccn/sn94056869/1918-04-18/ed-1.json"}, {"date_issued": "1918-04-25", "url": "http://chroniclingamerica.loc.gov/lccn/sn94056869/1918-04-25/ed-1.json"}, {"date_issued": "1918-05-02", "url": "http://chroniclingamerica.loc.gov/lccn/sn94056869/1918-05-02/ed-1.json"}, {"date_issued": "1918-05-09", "url": "http://chroniclingamerica.loc.gov/lccn/sn94056869/1918-05-09/ed-1.json"}, {"date_issued": "1918-05-16", "url": "http://chroniclingamerica.loc.gov/lccn/sn94056869/1918-05-16/ed-1.json"}, {"date_issued": "1918-05-23", "url": "http://chroniclingamerica.loc.gov/lccn/sn94056869/1918-05-23/ed-1.json"}, {"date_issued": "1918-05-30", "url": "http://chroniclingamerica.loc.gov/lccn/sn94056869/1918-05-30/ed-1.json"}, {"date_issued": "1918-06-06", "url": "http://chroniclingamerica.loc.gov/lccn/sn94056869/1918-06-06/ed-1.json"}, {"date_issued": "1918-06-13", "url": "http://chroniclingamerica.loc.gov/lccn/sn94056869/1918-06-13/ed-1.json"}, {"date_issued": "1918-06-20", "url": "http://chroniclingamerica.loc.gov/lccn/sn94056869/1918-06-20/ed-1.json"}, {"date_issued": "1918-06-27", "url": "http://chroniclingamerica.loc.gov/lccn/sn94056869/1918-06-27/ed-1.json"}, {"date_issued": "1918-07-04", "url": "http://chroniclingamerica.loc.gov/lccn/sn94056869/1918-07-04/ed-1.json"}, {"date_issued": "1918-07-11", "url": "http://chroniclingamerica.loc.gov/lccn/sn94056869/1918-07-11/ed-1.json"}, {"date_issued": "1918-07-25", "url": "http://chroniclingamerica.loc.gov/lccn/sn94056869/1918-07-25/ed-1.json"}, {"date_issued": "1918-08-01", "url": "http://chroniclingamerica.loc.gov/lccn/sn94056869/1918-08-01/ed-1.json"}, {"date_issued": "1918-08-08", "url": "http://chroniclingamerica.loc.gov/lccn/sn94056869/1918-08-08/ed-1.json"}, {"date_issued": "1918-08-15", "url": "http://chroniclingamerica.loc.gov/lccn/sn94056869/1918-08-15/ed-1.json"}, {"date_issued": "1918-08-22", "url": "http://chroniclingamerica.loc.gov/lccn/sn94056869/1918-08-22/ed-1.json"}, {"date_issued": "1918-08-29", "url": "http://chroniclingamerica.loc.gov/lccn/sn94056869/1918-08-29/ed-1.json"}, {"date_issued": "1918-09-05", "url": "http://chroniclingamerica.loc.gov/lccn/sn94056869/1918-09-05/ed-1.json"}, {"date_issued": "1918-09-12", "url": "http://chroniclingamerica.loc.gov/lccn/sn94056869/1918-09-12/ed-1.json"}, {"date_issued": "1918-09-19", "url": "http://chroniclingamerica.loc.gov/lccn/sn94056869/1918-09-19/ed-1.json"}, {"date_issued": "1918-09-26", "url": "http://chroniclingamerica.loc.gov/lccn/sn94056869/1918-09-26/ed-1.json"}, {"date_issued": "1918-10-03", "url": "http://chroniclingamerica.loc.gov/lccn/sn94056869/1918-10-03/ed-1.json"}, {"date_issued": "1918-10-10", "url": "http://chroniclingamerica.loc.gov/lccn/sn94056869/1918-10-10/ed-1.json"}, {"date_issued": "1918-10-17", "url": "http://chroniclingamerica.loc.gov/lccn/sn94056869/1918-10-17/ed-1.json"}, {"date_issued": "1918-11-07", "url": "http://chroniclingamerica.loc.gov/lccn/sn94056869/1918-11-07/ed-1.json"}, {"date_issued": "1919-01-02", "url": "http://chroniclingamerica.loc.gov/lccn/sn94056869/1919-01-02/ed-1.json"}, {"date_issued": "1919-01-09", "url": "http://chroniclingamerica.loc.gov/lccn/sn94056869/1919-01-09/ed-1.json"}, {"date_issued": "1919-01-16", "url": "http://chroniclingamerica.loc.gov/lccn/sn94056869/1919-01-16/ed-1.json"}, {"date_issued": "1919-01-23", "url": "http://chroniclingamerica.loc.gov/lccn/sn94056869/1919-01-23/ed-1.json"}, {"date_issued": "1919-01-30", "url": "http://chroniclingamerica.loc.gov/lccn/sn94056869/1919-01-30/ed-1.json"}, {"date_issued": "1919-02-06", "url": "http://chroniclingamerica.loc.gov/lccn/sn94056869/1919-02-06/ed-1.json"}, {"date_issued": "1919-02-13", "url": "http://chroniclingamerica.loc.gov/lccn/sn94056869/1919-02-13/ed-1.json"}, {"date_issued": "1919-02-20", "url": "http://chroniclingamerica.loc.gov/lccn/sn94056869/1919-02-20/ed-1.json"}, {"date_issued": "1919-02-27", "url": "http://chroniclingamerica.loc.gov/lccn/sn94056869/1919-02-27/ed-1.json"}, {"date_issued": "1919-03-06", "url": "http://chroniclingamerica.loc.gov/lccn/sn94056869/1919-03-06/ed-1.json"}, {"date_issued": "1919-03-13", "url": "http://chroniclingamerica.loc.gov/lccn/sn94056869/1919-03-13/ed-1.json"}, {"date_issued": "1919-03-20", "url": "http://chroniclingamerica.loc.gov/lccn/sn94056869/1919-03-20/ed-1.json"}, {"date_issued": "1919-03-27", "url": "http://chroniclingamerica.loc.gov/lccn/sn94056869/1919-03-27/ed-1.json"}, {"date_issued": "1919-04-03", "url": "http://chroniclingamerica.loc.gov/lccn/sn94056869/1919-04-03/ed-1.json"}, {"date_issued": "1919-04-10", "url": "http://chroniclingamerica.loc.gov/lccn/sn94056869/1919-04-10/ed-1.json"}, {"date_issued": "1919-04-17", "url": "http://chroniclingamerica.loc.gov/lccn/sn94056869/1919-04-17/ed-1.json"}, {"date_issued": "1919-04-24", "url": "http://chroniclingamerica.loc.gov/lccn/sn94056869/1919-04-24/ed-1.json"}, {"date_issued": "1919-05-01", "url": "http://chroniclingamerica.loc.gov/lccn/sn94056869/1919-05-01/ed-1.json"}, {"date_issued": "1919-05-08", "url": "http://chroniclingamerica.loc.gov/lccn/sn94056869/1919-05-08/ed-1.json"}, {"date_issued": "1919-05-15", "url": "http://chroniclingamerica.loc.gov/lccn/sn94056869/1919-05-15/ed-1.json"}, {"date_issued": "1919-05-22", "url": "http://chroniclingamerica.loc.gov/lccn/sn94056869/1919-05-22/ed-1.json"}, {"date_issued": "1919-05-29", "url": "http://chroniclingamerica.loc.gov/lccn/sn94056869/1919-05-29/ed-1.json"}, {"date_issued": "1919-06-05", "url": "http://chroniclingamerica.loc.gov/lccn/sn94056869/1919-06-05/ed-1.json"}, {"date_issued": "1919-06-12", "url": "http://chroniclingamerica.loc.gov/lccn/sn94056869/1919-06-12/ed-1.json"}, {"date_issued": "1919-06-19", "url": "http://chroniclingamerica.loc.gov/lccn/sn94056869/1919-06-19/ed-1.json"}, {"date_issued": "1919-06-26", "url": "http://chroniclingamerica.loc.gov/lccn/sn94056869/1919-06-26/ed-1.json"}, {"date_issued": "1919-07-03", "url": "http://chroniclingamerica.loc.gov/lccn/sn94056869/1919-07-03/ed-1.json"}, {"date_issued": "1919-07-10", "url": "http://chroniclingamerica.loc.gov/lccn/sn94056869/1919-07-10/ed-1.json"}, {"date_issued": "1919-07-17", "url": "http://chroniclingamerica.loc.gov/lccn/sn94056869/1919-07-17/ed-1.json"}, {"date_issued": "1919-07-24", "url": "http://chroniclingamerica.loc.gov/lccn/sn94056869/1919-07-24/ed-1.json"}, {"date_issued": "1919-07-31", "url": "http://chroniclingamerica.loc.gov/lccn/sn94056869/1919-07-31/ed-1.json"}, {"date_issued": "1919-08-07", "url": "http://chroniclingamerica.loc.gov/lccn/sn94056869/1919-08-07/ed-1.json"}, {"date_issued": "1919-08-14", "url": "http://chroniclingamerica.loc.gov/lccn/sn94056869/1919-08-14/ed-1.json"}, {"date_issued": "1919-08-21", "url": "http://chroniclingamerica.loc.gov/lccn/sn94056869/1919-08-21/ed-1.json"}, {"date_issued": "1919-08-28", "url": "http://chroniclingamerica.loc.gov/lccn/sn94056869/1919-08-28/ed-1.json"}, {"date_issued": "1919-09-04", "url": "http://chroniclingamerica.loc.gov/lccn/sn94056869/1919-09-04/ed-1.json"}, {"date_issued": "1919-09-18", "url": "http://chroniclingamerica.loc.gov/lccn/sn94056869/1919-09-18/ed-1.json"}, {"date_issued": "1919-09-25", "url": "http://chroniclingamerica.loc.gov/lccn/sn94056869/1919-09-25/ed-1.json"}, {"date_issued": "1919-10-02", "url": "http://chroniclingamerica.loc.gov/lccn/sn94056869/1919-10-02/ed-1.json"}, {"date_issued": "1919-10-09", "url": "http://chroniclingamerica.loc.gov/lccn/sn94056869/1919-10-09/ed-1.json"}, {"date_issued": "1919-10-16", "url": "http://chroniclingamerica.loc.gov/lccn/sn94056869/1919-10-16/ed-1.json"}, {"date_issued": "1919-10-23", "url": "http://chroniclingamerica.loc.gov/lccn/sn94056869/1919-10-23/ed-1.json"}, {"date_issued": "1919-10-30", "url": "http://chroniclingamerica.loc.gov/lccn/sn94056869/1919-10-30/ed-1.json"}, {"date_issued": "1919-11-06", "url": "http://chroniclingamerica.loc.gov/lccn/sn94056869/1919-11-06/ed-1.json"}, {"date_issued": "1919-11-13", "url": "http://chroniclingamerica.loc.gov/lccn/sn94056869/1919-11-13/ed-1.json"}, {"date_issued": "1919-11-20", "url": "http://chroniclingamerica.loc.gov/lccn/sn94056869/1919-11-20/ed-1.json"}, {"date_issued": "1919-11-27", "url": "http://chroniclingamerica.loc.gov/lccn/sn94056869/1919-11-27/ed-1.json"}, {"date_issued": "1919-12-04", "url": "http://chroniclingamerica.loc.gov/lccn/sn94056869/1919-12-04/ed-1.json"}, {"date_issued": "1919-12-11", "url": "http://chroniclingamerica.loc.gov/lccn/sn94056869/1919-12-11/ed-1.json"}, {"date_issued": "1919-12-18", "url": "http://chroniclingamerica.loc.gov/lccn/sn94056869/1919-12-18/ed-1.json"}, {"date_issued": "1919-12-25", "url": "http://chroniclingamerica.loc.gov/lccn/sn94056869/1919-12-25/ed-1.json"}, {"date_issued": "1920-01-01", "url": "http://chroniclingamerica.loc.gov/lccn/sn94056869/1920-01-01/ed-1.json"}, {"date_issued": "1920-01-08", "url": "http://chroniclingamerica.loc.gov/lccn/sn94056869/1920-01-08/ed-1.json"}, {"date_issued": "1920-01-15", "url": "http://chroniclingamerica.loc.gov/lccn/sn94056869/1920-01-15/ed-1.json"}, {"date_issued": "1920-01-22", "url": "http://chroniclingamerica.loc.gov/lccn/sn94056869/1920-01-22/ed-1.json"}, {"date_issued": "1920-01-29", "url": "http://chroniclingamerica.loc.gov/lccn/sn94056869/1920-01-29/ed-1.json"}, {"date_issued": "1920-02-05", "url": "http://chroniclingamerica.loc.gov/lccn/sn94056869/1920-02-05/ed-1.json"}, {"date_issued": "1920-02-12", "url": "http://chroniclingamerica.loc.gov/lccn/sn94056869/1920-02-12/ed-1.json"}, {"date_issued": "1920-02-19", "url": "http://chroniclingamerica.loc.gov/lccn/sn94056869/1920-02-19/ed-1.json"}, {"date_issued": "1920-02-26", "url": "http://chroniclingamerica.loc.gov/lccn/sn94056869/1920-02-26/ed-1.json"}, {"date_issued": "1920-03-04", "url": "http://chroniclingamerica.loc.gov/lccn/sn94056869/1920-03-04/ed-1.json"}, {"date_issued": "1920-03-11", "url": "http://chroniclingamerica.loc.gov/lccn/sn94056869/1920-03-11/ed-1.json"}, {"date_issued": "1920-03-18", "url": "http://chroniclingamerica.loc.gov/lccn/sn94056869/1920-03-18/ed-1.json"}, {"date_issued": "1920-03-25", "url": "http://chroniclingamerica.loc.gov/lccn/sn94056869/1920-03-25/ed-1.json"}, {"date_issued": "1920-04-01", "url": "http://chroniclingamerica.loc.gov/lccn/sn94056869/1920-04-01/ed-1.json"}, {"date_issued": "1920-04-08", "url": "http://chroniclingamerica.loc.gov/lccn/sn94056869/1920-04-08/ed-1.json"}, {"date_issued": "1920-04-15", "url": "http://chroniclingamerica.loc.gov/lccn/sn94056869/1920-04-15/ed-1.json"}, {"date_issued": "1920-04-22", "url": "http://chroniclingamerica.loc.gov/lccn/sn94056869/1920-04-22/ed-1.json"}, {"date_issued": "1920-04-29", "url": "http://chroniclingamerica.loc.gov/lccn/sn94056869/1920-04-29/ed-1.json"}, {"date_issued": "1920-05-06", "url": "http://chroniclingamerica.loc.gov/lccn/sn94056869/1920-05-06/ed-1.json"}, {"date_issued": "1920-05-13", "url": "http://chroniclingamerica.loc.gov/lccn/sn94056869/1920-05-13/ed-1.json"}, {"date_issued": "1920-05-20", "url": "http://chroniclingamerica.loc.gov/lccn/sn94056869/1920-05-20/ed-1.json"}, {"date_issued": "1920-05-27", "url": "http://chroniclingamerica.loc.gov/lccn/sn94056869/1920-05-27/ed-1.json"}, {"date_issued": "1920-06-03", "url": "http://chroniclingamerica.loc.gov/lccn/sn94056869/1920-06-03/ed-1.json"}, {"date_issued": "1920-06-10", "url": "http://chroniclingamerica.loc.gov/lccn/sn94056869/1920-06-10/ed-1.json"}, {"date_issued": "1920-06-17", "url": "http://chroniclingamerica.loc.gov/lccn/sn94056869/1920-06-17/ed-1.json"}, {"date_issued": "1920-06-24", "url": "http://chroniclingamerica.loc.gov/lccn/sn94056869/1920-06-24/ed-1.json"}, {"date_issued": "1920-07-01", "url": "http://chroniclingamerica.loc.gov/lccn/sn94056869/1920-07-01/ed-1.json"}, {"date_issued": "1920-07-08", "url": "http://chroniclingamerica.loc.gov/lccn/sn94056869/1920-07-08/ed-1.json"}, {"date_issued": "1920-07-15", "url": "http://chroniclingamerica.loc.gov/lccn/sn94056869/1920-07-15/ed-1.json"}, {"date_issued": "1920-07-22", "url": "http://chroniclingamerica.loc.gov/lccn/sn94056869/1920-07-22/ed-1.json"}, {"date_issued": "1920-07-29", "url": "http://chroniclingamerica.loc.gov/lccn/sn94056869/1920-07-29/ed-1.json"}, {"date_issued": "1920-08-05", "url": "http://chroniclingamerica.loc.gov/lccn/sn94056869/1920-08-05/ed-1.json"}, {"date_issued": "1920-08-12", "url": "http://chroniclingamerica.loc.gov/lccn/sn94056869/1920-08-12/ed-1.json"}, {"date_issued": "1920-08-19", "url": "http://chroniclingamerica.loc.gov/lccn/sn94056869/1920-08-19/ed-1.json"}, {"date_issued": "1920-08-26", "url": "http://chroniclingamerica.loc.gov/lccn/sn94056869/1920-08-26/ed-1.json"}, {"date_issued": "1920-09-09", "url": "http://chroniclingamerica.loc.gov/lccn/sn94056869/1920-09-09/ed-1.json"}, {"date_issued": "1920-09-16", "url": "http://chroniclingamerica.loc.gov/lccn/sn94056869/1920-09-16/ed-1.json"}, {"date_issued": "1920-09-23", "url": "http://chroniclingamerica.loc.gov/lccn/sn94056869/1920-09-23/ed-1.json"}, {"date_issued": "1920-09-30", "url": "http://chroniclingamerica.loc.gov/lccn/sn94056869/1920-09-30/ed-1.json"}, {"date_issued": "1920-10-07", "url": "http://chroniclingamerica.loc.gov/lccn/sn94056869/1920-10-07/ed-1.json"}, {"date_issued": "1920-10-14", "url": "http://chroniclingamerica.loc.gov/lccn/sn94056869/1920-10-14/ed-1.json"}, {"date_issued": "1920-10-21", "url": "http://chroniclingamerica.loc.gov/lccn/sn94056869/1920-10-21/ed-1.json"}, {"date_issued": "1920-10-28", "url": "http://chroniclingamerica.loc.gov/lccn/sn94056869/1920-10-28/ed-1.json"}, {"date_issued": "1920-11-04", "url": "http://chroniclingamerica.loc.gov/lccn/sn94056869/1920-11-04/ed-1.json"}, {"date_issued": "1920-11-11", "url": "http://chroniclingamerica.loc.gov/lccn/sn94056869/1920-11-11/ed-1.json"}, {"date_issued": "1920-11-18", "url": "http://chroniclingamerica.loc.gov/lccn/sn94056869/1920-11-18/ed-1.json"}, {"date_issued": "1920-11-25", "url": "http://chroniclingamerica.loc.gov/lccn/sn94056869/1920-11-25/ed-1.json"}, {"date_issued": "1920-12-02", "url": "http://chroniclingamerica.loc.gov/lccn/sn94056869/1920-12-02/ed-1.json"}, {"date_issued": "1920-12-09", "url": "http://chroniclingamerica.loc.gov/lccn/sn94056869/1920-12-09/ed-1.json"}, {"date_issued": "1920-12-16", "url": "http://chroniclingamerica.loc.gov/lccn/sn94056869/1920-12-16/ed-1.json"}, {"date_issued": "1920-12-23", "url": "http://chroniclingamerica.loc.gov/lccn/sn94056869/1920-12-23/ed-1.json"}, {"date_issued": "1920-12-30", "url": "http://chroniclingamerica.loc.gov/lccn/sn94056869/1920-12-30/ed-1.json"}, {"date_issued": "1921-01-06", "url": "http://chroniclingamerica.loc.gov/lccn/sn94056869/1921-01-06/ed-1.json"}, {"date_issued": "1921-01-13", "url": "http://chroniclingamerica.loc.gov/lccn/sn94056869/1921-01-13/ed-1.json"}, {"date_issued": "1921-01-20", "url": "http://chroniclingamerica.loc.gov/lccn/sn94056869/1921-01-20/ed-1.json"}, {"date_issued": "1921-01-27", "url": "http://chroniclingamerica.loc.gov/lccn/sn94056869/1921-01-27/ed-1.json"}, {"date_issued": "1921-02-03", "url": "http://chroniclingamerica.loc.gov/lccn/sn94056869/1921-02-03/ed-1.json"}, {"date_issued": "1921-02-10", "url": "http://chroniclingamerica.loc.gov/lccn/sn94056869/1921-02-10/ed-1.json"}, {"date_issued": "1921-02-17", "url": "http://chroniclingamerica.loc.gov/lccn/sn94056869/1921-02-17/ed-1.json"}, {"date_issued": "1921-02-24", "url": "http://chroniclingamerica.loc.gov/lccn/sn94056869/1921-02-24/ed-1.json"}, {"date_issued": "1921-03-03", "url": "http://chroniclingamerica.loc.gov/lccn/sn94056869/1921-03-03/ed-1.json"}, {"date_issued": "1921-03-10", "url": "http://chroniclingamerica.loc.gov/lccn/sn94056869/1921-03-10/ed-1.json"}, {"date_issued": "1921-03-17", "url": "http://chroniclingamerica.loc.gov/lccn/sn94056869/1921-03-17/ed-1.json"}, {"date_issued": "1921-03-24", "url": "http://chroniclingamerica.loc.gov/lccn/sn94056869/1921-03-24/ed-1.json"}, {"date_issued": "1921-03-31", "url": "http://chroniclingamerica.loc.gov/lccn/sn94056869/1921-03-31/ed-1.json"}, {"date_issued": "1921-04-07", "url": "http://chroniclingamerica.loc.gov/lccn/sn94056869/1921-04-07/ed-1.json"}, {"date_issued": "1921-04-14", "url": "http://chroniclingamerica.loc.gov/lccn/sn94056869/1921-04-14/ed-1.json"}, {"date_issued": "1921-04-21", "url": "http://chroniclingamerica.loc.gov/lccn/sn94056869/1921-04-21/ed-1.json"}, {"date_issued": "1921-04-28", "url": "http://chroniclingamerica.loc.gov/lccn/sn94056869/1921-04-28/ed-1.json"}, {"date_issued": "1921-05-05", "url": "http://chroniclingamerica.loc.gov/lccn/sn94056869/1921-05-05/ed-1.json"}, {"date_issued": "1921-05-12", "url": "http://chroniclingamerica.loc.gov/lccn/sn94056869/1921-05-12/ed-1.json"}, {"date_issued": "1921-05-19", "url": "http://chroniclingamerica.loc.gov/lccn/sn94056869/1921-05-19/ed-1.json"}, {"date_issued": "1921-05-26", "url": "http://chroniclingamerica.loc.gov/lccn/sn94056869/1921-05-26/ed-1.json"}, {"date_issued": "1921-06-09", "url": "http://chroniclingamerica.loc.gov/lccn/sn94056869/1921-06-09/ed-1.json"}, {"date_issued": "1921-06-16", "url": "http://chroniclingamerica.loc.gov/lccn/sn94056869/1921-06-16/ed-1.json"}, {"date_issued": "1921-06-23", "url": "http://chroniclingamerica.loc.gov/lccn/sn94056869/1921-06-23/ed-1.json"}, {"date_issued": "1921-07-07", "url": "http://chroniclingamerica.loc.gov/lccn/sn94056869/1921-07-07/ed-1.json"}, {"date_issued": "1921-07-14", "url": "http://chroniclingamerica.loc.gov/lccn/sn94056869/1921-07-14/ed-1.json"}, {"date_issued": "1921-07-21", "url": "http://chroniclingamerica.loc.gov/lccn/sn94056869/1921-07-21/ed-1.json"}, {"date_issued": "1921-07-28", "url": "http://chroniclingamerica.loc.gov/lccn/sn94056869/1921-07-28/ed-1.json"}, {"date_issued": "1921-08-04", "url": "http://chroniclingamerica.loc.gov/lccn/sn94056869/1921-08-04/ed-1.json"}, {"date_issued": "1921-08-11", "url": "http://chroniclingamerica.loc.gov/lccn/sn94056869/1921-08-11/ed-1.json"}, {"date_issued": "1921-08-18", "url": "http://chroniclingamerica.loc.gov/lccn/sn94056869/1921-08-18/ed-1.json"}, {"date_issued": "1921-08-25", "url": "http://chroniclingamerica.loc.gov/lccn/sn94056869/1921-08-25/ed-1.json"}, {"date_issued": "1921-09-01", "url": "http://chroniclingamerica.loc.gov/lccn/sn94056869/1921-09-01/ed-1.json"}, {"date_issued": "1921-09-08", "url": "http://chroniclingamerica.loc.gov/lccn/sn94056869/1921-09-08/ed-1.json"}, {"date_issued": "1921-09-15", "url": "http://chroniclingamerica.loc.gov/lccn/sn94056869/1921-09-15/ed-1.json"}, {"date_issued": "1921-09-22", "url": "http://chroniclingamerica.loc.gov/lccn/sn94056869/1921-09-22/ed-1.json"}, {"date_issued": "1921-09-29", "url": "http://chroniclingamerica.loc.gov/lccn/sn94056869/1921-09-29/ed-1.json"}, {"date_issued": "1921-10-06", "url": "http://chroniclingamerica.loc.gov/lccn/sn94056869/1921-10-06/ed-1.json"}, {"date_issued": "1921-10-13", "url": "http://chroniclingamerica.loc.gov/lccn/sn94056869/1921-10-13/ed-1.json"}, {"date_issued": "1921-10-20", "url": "http://chroniclingamerica.loc.gov/lccn/sn94056869/1921-10-20/ed-1.json"}, {"date_issued": "1921-10-27", "url": "http://chroniclingamerica.loc.gov/lccn/sn94056869/1921-10-27/ed-1.json"}, {"date_issued": "1921-11-03", "url": "http://chroniclingamerica.loc.gov/lccn/sn94056869/1921-11-03/ed-1.json"}, {"date_issued": "1921-11-10", "url": "http://chroniclingamerica.loc.gov/lccn/sn94056869/1921-11-10/ed-1.json"}, {"date_issued": "1921-11-17", "url": "http://chroniclingamerica.loc.gov/lccn/sn94056869/1921-11-17/ed-1.json"}, {"date_issued": "1921-11-24", "url": "http://chroniclingamerica.loc.gov/lccn/sn94056869/1921-11-24/ed-1.json"}, {"date_issued": "1921-12-01", "url": "http://chroniclingamerica.loc.gov/lccn/sn94056869/1921-12-01/ed-1.json"}, {"date_issued": "1921-12-08", "url": "http://chroniclingamerica.loc.gov/lccn/sn94056869/1921-12-08/ed-1.json"}, {"date_issued": "1921-12-15", "url": "http://chroniclingamerica.loc.gov/lccn/sn94056869/1921-12-15/ed-1.json"}, {"date_issued": "1921-12-22", "url": "http://chroniclingamerica.loc.gov/lccn/sn94056869/1921-12-22/ed-1.json"}, {"date_issued": "1921-12-29", "url": "http://chroniclingamerica.loc.gov/lccn/sn94056869/1921-12-29/ed-1.json"}, {"date_issued": "1922-01-05", "url": "http://chroniclingamerica.loc.gov/lccn/sn94056869/1922-01-05/ed-1.json"}, {"date_issued": "1922-01-12", "url": "http://chroniclingamerica.loc.gov/lccn/sn94056869/1922-01-12/ed-1.json"}, {"date_issued": "1922-01-19", "url": "http://chroniclingamerica.loc.gov/lccn/sn94056869/1922-01-19/ed-1.json"}, {"date_issued": "1922-01-26", "url": "http://chroniclingamerica.loc.gov/lccn/sn94056869/1922-01-26/ed-1.json"}, {"date_issued": "1922-02-02", "url": "http://chroniclingamerica.loc.gov/lccn/sn94056869/1922-02-02/ed-1.json"}, {"date_issued": "1922-02-09", "url": "http://chroniclingamerica.loc.gov/lccn/sn94056869/1922-02-09/ed-1.json"}, {"date_issued": "1922-02-16", "url": "http://chroniclingamerica.loc.gov/lccn/sn94056869/1922-02-16/ed-1.json"}, {"date_issued": "1922-02-23", "url": "http://chroniclingamerica.loc.gov/lccn/sn94056869/1922-02-23/ed-1.json"}, {"date_issued": "1922-03-02", "url": "http://chroniclingamerica.loc.gov/lccn/sn94056869/1922-03-02/ed-1.json"}, {"date_issued": "1922-03-09", "url": "http://chroniclingamerica.loc.gov/lccn/sn94056869/1922-03-09/ed-1.json"}, {"date_issued": "1922-03-16", "url": "http://chroniclingamerica.loc.gov/lccn/sn94056869/1922-03-16/ed-1.json"}, {"date_issued": "1922-03-23", "url": "http://chroniclingamerica.loc.gov/lccn/sn94056869/1922-03-23/ed-1.json"}, {"date_issued": "1922-03-30", "url": "http://chroniclingamerica.loc.gov/lccn/sn94056869/1922-03-30/ed-1.json"}, {"date_issued": "1922-04-06", "url": "http://chroniclingamerica.loc.gov/lccn/sn94056869/1922-04-06/ed-1.json"}, {"date_issued": "1922-04-13", "url": "http://chroniclingamerica.loc.gov/lccn/sn94056869/1922-04-13/ed-1.json"}, {"date_issued": "1922-04-20", "url": "http://chroniclingamerica.loc.gov/lccn/sn94056869/1922-04-20/ed-1.json"}, {"date_issued": "1922-04-27", "url": "http://chroniclingamerica.loc.gov/lccn/sn94056869/1922-04-27/ed-1.json"}, {"date_issued": "1922-05-04", "url": "http://chroniclingamerica.loc.gov/lccn/sn94056869/1922-05-04/ed-1.json"}, {"date_issued": "1922-05-11", "url": "http://chroniclingamerica.loc.gov/lccn/sn94056869/1922-05-11/ed-1.json"}, {"date_issued": "1922-05-18", "url": "http://chroniclingamerica.loc.gov/lccn/sn94056869/1922-05-18/ed-1.json"}, {"date_issued": "1922-05-25", "url": "http://chroniclingamerica.loc.gov/lccn/sn94056869/1922-05-25/ed-1.json"}, {"date_issued": "1922-06-01", "url": "http://chroniclingamerica.loc.gov/lccn/sn94056869/1922-06-01/ed-1.json"}, {"date_issued": "1922-06-08", "url": "http://chroniclingamerica.loc.gov/lccn/sn94056869/1922-06-08/ed-1.json"}, {"date_issued": "1922-06-15", "url": "http://chroniclingamerica.loc.gov/lccn/sn94056869/1922-06-15/ed-1.json"}, {"date_issued": "1922-06-22", "url": "http://chroniclingamerica.loc.gov/lccn/sn94056869/1922-06-22/ed-1.json"}, {"date_issued": "1922-06-29", "url": "http://chroniclingamerica.loc.gov/lccn/sn94056869/1922-06-29/ed-1.json"}, {"date_issued": "1922-07-06", "url": "http://chroniclingamerica.loc.gov/lccn/sn94056869/1922-07-06/ed-1.json"}, {"date_issued": "1922-07-13", "url": "http://chroniclingamerica.loc.gov/lccn/sn94056869/1922-07-13/ed-1.json"}, {"date_issued": "1922-07-20", "url": "http://chroniclingamerica.loc.gov/lccn/sn94056869/1922-07-20/ed-1.json"}, {"date_issued": "1922-07-27", "url": "http://chroniclingamerica.loc.gov/lccn/sn94056869/1922-07-27/ed-1.json"}, {"date_issued": "1922-08-10", "url": "http://chroniclingamerica.loc.gov/lccn/sn94056869/1922-08-10/ed-1.json"}, {"date_issued": "1922-08-17", "url": "http://chroniclingamerica.loc.gov/lccn/sn94056869/1922-08-17/ed-1.json"}, {"date_issued": "1922-08-24", "url": "http://chroniclingamerica.loc.gov/lccn/sn94056869/1922-08-24/ed-1.json"}, {"date_issued": "1922-08-31", "url": "http://chroniclingamerica.loc.gov/lccn/sn94056869/1922-08-31/ed-1.json"}, {"date_issued": "1922-09-07", "url": "http://chroniclingamerica.loc.gov/lccn/sn94056869/1922-09-07/ed-1.json"}, {"date_issued": "1922-09-14", "url": "http://chroniclingamerica.loc.gov/lccn/sn94056869/1922-09-14/ed-1.json"}, {"date_issued": "1922-09-21", "url": "http://chroniclingamerica.loc.gov/lccn/sn94056869/1922-09-21/ed-1.json"}, {"date_issued": "1922-09-28", "url": "http://chroniclingamerica.loc.gov/lccn/sn94056869/1922-09-28/ed-1.json"}], "name": "El Nuevo mexicano.", "subject": ["Hispanic Americans--New Mexico--Newspapers.", "Hispanic Americans.--fast--(OCoLC)fst00957523", "New Mexico--Santa Fe County.--fast--(OCoLC)fst01216898", "New Mexico--Santa Fe.--fast--(OCoLC)fst01205208", "New Mexico.--fast--(OCoLC)fst01204269", "Santa Fe (N.M.)--Newspapers.", "Santa Fe County (N.M.)--Newspapers."], "publisher": "La Ci\u0301a. Publicista de Nuevo Mexicano"}